Workbook

Sheet Instructions
B2: How to Use This Model
B3: Update the Inputs sheet only. Every other worksheet is formula-driven and updates automatically.
B5: Worksheet | C5: Instructions
B6: Inputs | C6: This is the only worksheet you edit: growth and margins for each case, shared operating assumptions and valuation inputs.
B7: Summary | C7: Rating, price target, a side-by-side comparison of the four cases, the valuation range and model checks. Use the dropdown to look at one case.
B8: Base / Bull / Bear / Priced In | C8: No manual data entry needed. Full income statement, balance sheet, cash flow and DCF for each case.
B9: WACC | C9: No manual data entry needed. Cost of debt from Tapestry's own bonds, cost of equity from CAPM.
B10: Comps | C10: Trading multiples for nine peers and what they imply for Tapestry.
B11: Sensitivity | C11: No manual data entry needed. Base case value across WACC and terminal growth.
B12: Historicals | C12: Reported financials from the FY2026 10-K and earnings release, with sources.
B13: Market Data | C13: Share price, guidance, rates and analyst targets, with sources.
B15: What I built
B16: The company | C16: Tapestry (Coach, Kate Spade). FY2026 sales of $8.0B, with Coach up 24%. The stock is down about 30% from its August high.
B17: Three statements | C17: Five years of projections by brand, with a balance sheet that balances and a cash flow statement that drives cash, buybacks and share count.
B18: Valuation | C18: A DCF with a stub period from today to the end of FY2027, a peer comparison and a WACC built from Tapestry's own bond prices.
B19: The question | C19: The Priced In case asks what Coach has to keep doing for today's price to make sense.
B21: Limitations
B22: Adjusted numbers | C22: Projections are on Tapestry's adjusted (non-GAAP) basis and assume no more one-time charges or tariff refunds.
B23: Leases | C23: Rent stays in operating costs, so lease liabilities are left out of the DCF on purpose. The comps use EV with leases, to match the data source.
B24: Data | C24: Peer multiples come from one data source on slightly different dates. The Priced In growth rate was solved outside the sheet.

Sheet Summary
B2: Tapestry, Inc. (NYSE: TPR): Valuation Summary
B3: Equity research model by Deepangi Arora. Priced as of October 8, 2026. $ in millions except per share.
B5: Recommendation
B6: Item | C6: Value
B7: Share price (Oct 8, 2026) | C7: =Inputs!$C$53 -> 115.82
B8: Base case DCF value today | C8: =Base!$D$97 -> 104.60259
B9: 12-month price target | C9: =ROUND(C8*(1+WACC!$C$19)-Inputs!$C$42,0) -> 115
B10: Upside / (downside) to target | C10: =C9/C7-1 -> -0.0070799516
B11: Rating | C11: =IF(C10>0.15,"BUY",IF(C10<-0.15,"SELL","HOLD")) -> HOLD
B12: Target = today's DCF value grown at the cost of equity for a year, less the dividend. BUY above +15%, SELL below -15%.
B14: Quick Case View
B15: Choose a case from the dropdown below.
B16: Case | C16: Base
B17: Value per share | C17: =INDEX($C$26:$F$26,MATCH($C$16,$C$25:$F$25,0)) -> 104.60259
B18: Upside / (downside) vs price | C18: =INDEX($C$27:$F$27,MATCH($C$16,$C$25:$F$25,0)) -> -0.096852084
B19: FY2027 EPS | C19: =INDEX($C$28:$F$28,MATCH($C$16,$C$25:$F$25,0)) -> 7.9266774
B20: FY2028 EPS | C20: =INDEX($C$29:$F$29,MATCH($C$16,$C$25:$F$25,0)) -> 8.7401774
B21: Coach sales growth, FY2026 to FY2031 (per year) | C21: =INDEX($C$30:$F$30,MATCH($C$16,$C$25:$F$25,0)) -> 0.053713554
B22: FY2031 operating margin | C22: =INDEX($C$32:$F$32,MATCH($C$16,$C$25:$F$25,0)) -> 0.245
B24: Case Comparison
B25: Metric | C25: Base | D25: Bull | E25: Bear | F25: Priced In
B26: Value per share | C26: =Base!$D$97 -> 104.60259 | D26: =Bull!$D$97 -> 123.66411 | E26: =Bear!$D$97 -> 73.213088 | F26: ='Priced In'!$D$97 -> 115.74847
B27: Upside / (downside) vs price | C27: =Base!$D$98 -> -0.096852084 | D27: =Bull!$D$98 -> 0.067726701 | E27: =Bear!$D$98 -> -0.3678718 | F27: ='Priced In'!$D$98 -> -0.00061761816
B28: FY2027 EPS | C28: =Base!$E$28 -> 7.9266774 | D28: =Bull!$E$28 -> 8.0733585 | E28: =Bear!$E$28 -> 7.6604555 | F28: ='Priced In'!$E$28 -> 7.9266774
B29: FY2028 EPS | C29: =Base!$F$28 -> 8.7401774 | D29: =Bull!$F$28 -> 9.4960087 | E29: =Bear!$F$28 -> 7.3084948 | F29: ='Priced In'!$F$28 -> 8.9318319
B30: Coach sales growth, FY2026 to FY2031 (per year) | C30: =(Base!$I$8/Base!$D$8)^(1/5)-1 -> 0.053713554 | D30: =(Bull!$I$8/Bull!$D$8)^(1/5)-1 -> 0.077936751 | E30: =(Bear!$I$8/Bear!$D$8)^(1/5)-1 -> 0.013656238 | F30: =('Priced In'!$I$8/'Priced In'!$D$8)^(1/5)-1 -> 0.079
B31: FY2031 net sales | C31: =Base!$I$12 -> 9970.4813 | D31: =Bull!$I$12 -> 11156.663 | E31: =Bear!$I$12 -> 8290.822 | F31: ='Priced In'!$I$12 -> 11101.223
B32: FY2031 operating margin | C32: =Base!$I$20 -> 0.245 | D32: =Bull!$I$20 -> 0.26 | E32: =Bear!$I$20 -> 0.205 | F32: ='Priced In'!$I$20 -> 0.245
B33: FY2031 unlevered free cash flow | C33: =Base!$I$80 -> 1951.1729 | D33: =Bull!$I$80 -> 2327.6082 | E33: =Bear!$I$80 -> 1345.6058 | F33: ='Priced In'!$I$80 -> 2184.8693
B34: Terminal value as % of EV | C34: =Base!$D$99 -> 0.70566566 | D34: =Bull!$D$99 -> 0.71802615 | E34: =Bear!$D$99 -> 0.67957759 | F34: ='Priced In'!$D$99 -> 0.71782578
B36: Valuation Range (Football Field)
B37: Method | C37: Low | D37: High | G37: Note
B38: 52-week trading range | C38: ='Market Data'!$C$9 -> 93 | D38: ='Market Data'!$C$8 -> 164.8 | G38: Market Data.
B39: Analyst price targets | C39: ='Market Data'!$C$12 -> 138 | D39: ='Market Data'!$C$13 -> 232 | G39: Lowest and highest Street targets (MarketBeat).
B40: DCF: Bear to Bull case | C40: =Bear!$D$97 -> 73.213088 | D40: =Bull!$D$97 -> 123.66411 | G40: Case sheets.
B41: DCF: Base case, WACC +/- 1 point | C41: =Sensitivity!$G$11 -> 92.131365 | D41: =Sensitivity!$C$11 -> 120.8068 | G41: Sensitivity sheet.
B42: Peers: forward P/E (25th to 75th percentile) | C42: =Comps!$E$25 -> 95.456 | D42: =Comps!$E$27 -> 147.5015 | G42: Comps sheet.
B43: Peers: EV/EBIT (25th to 75th percentile) | C43: =Comps!$E$28 -> 98.455493 | D43: =Comps!$E$30 -> 200.28002 | G43: Comps sheet.
B44: Today's price | C44: =Inputs!$C$53 -> 115.82 | D44: =Inputs!$C$53 -> 115.82
B46: Model Checks
B47: Check | C47: Model | D47: Guidance low | E47: Guidance high | G47: Result
B48: Base FY2027 net sales vs guidance | C48: =Base!$E$12 -> 8449.8693 | D48: ='Market Data'!$C$17 -> 8400 | E48: ='Market Data'!$D$17 -> 8500 | G48: =IF(AND(C48>=D48,C48<=E48),"Inside guidance",IF(AND(C48>=D48*0.99,C48<=E48*1.01),"Within 1% of guidance","Off guidance")) -> Inside guidance
B49: Base FY2027 EPS vs guidance | C49: =Base!$E$28 -> 7.9266774 | D49: ='Market Data'!$C$18 -> 7.8 | E49: ='Market Data'!$D$18 -> 7.9 | G49: =IF(AND(C49>=D49,C49<=E49),"Inside guidance",IF(AND(C49>=D49*0.99,C49<=E49*1.01),"Within 1% of guidance","Off guidance")) -> Within 1% of guidance
B50: Base FY2027 free cash flow vs 'approaching $1.7B' | C50: =Base!$E$60 -> 1652.5541 | D50: ='Market Data'!$C$20*0.95 -> 1615 | E50: ='Market Data'!$D$20 -> 1700 | G50: =IF(AND(C50>=D50,C50<=E50),"Inside guidance",IF(AND(C50>=D50*0.99,C50<=E50*1.01),"Within 1% of guidance","Off guidance")) -> Inside guidance
B51: Balance sheets balance in every case | G51: =IF(SUMPRODUCT(ABS(Base!$E$50:$I$50))+SUMPRODUCT(ABS(Bull!$E$50:$I$50))+SUMPRODUCT(ABS(Bear!$E$50:$I$50))+SUMPRODUCT(ABS('Priced In'!$E$50:$I$50))<0.01,"Yes","No") -> Yes
B52: Sensitivity table center = Base value | G52: =IF(ABS(Sensitivity!$E$11-Base!$D$97)<0.005,"Yes","No") -> Yes
B53: Priced In case value vs today's price | C53: ='Priced In'!$D$97 -> 115.74847 | D53: =Inputs!$C$53 -> 115.82 | G53: =IF(ABS(C53/D53-1)<0.02,"Within 2% of price","Re-solve the Priced In growth") -> Within 2% of price

Sheet Inputs
B2: Inputs & Assumptions
B3: This is the only sheet that should be updated manually. Every other worksheet is formula-driven.
B5: Case Assumptions
B6: Each case runs on its own sheet. FY2026 base year is pro forma (excludes Stuart Weitzman).
B7: Coach revenue growth | C7: FY2027E | D7: FY2028E | E7: FY2029E | F7: FY2030E | G7: FY2031E | H7: Units | I7: Source / note
B8: Base | C8: 0.079 | D8: 0.055 | E8: 0.05 | F8: 0.045 | G8: 0.04 | H8: % | I8: FY2027 = what guidance implies for Coach once Kate Spade falls 8%. Then a slow fade toward 4%.
B9: Bull | C9: 0.09 | D9: 0.09 | E9: 0.08 | F9: 0.07 | G9: 0.06 | H9: % | I9: Coach keeps winning new customers and pricing power holds.
B10: Bear | C10: 0.06 | D10: 0 | E10: -0.02 | F10: 0.01 | G10: 0.02 | H10: % | I10: The handbag cycle turns, the way Michael Kors did after 2015.
B11: Priced In | C11: 0.079 | D11: 0.079 | E11: 0.079 | F11: 0.079 | G11: 0.079 | H11: % | I11: The constant Coach growth that makes the Base case DCF equal today's price (solved separately, rounded).
B13: Kate Spade revenue growth | C13: FY2027E | D13: FY2028E | E13: FY2029E | F13: FY2030E | G13: FY2031E | H13: Units | I13: Source / note
B14: Base | C14: -0.08 | D14: -0.03 | E14: 0 | F14: 0.01 | G14: 0.02 | H14: % | I14: Guidance: high single digit decline in FY2027, then the store closures finish.
B15: Bull | C15: -0.06 | D15: 0 | E15: 0.02 | F15: 0.03 | G15: 0.03 | H15: %
B16: Bear | C16: -0.1 | D16: -0.06 | E16: -0.03 | F16: 0 | G16: 0.01 | H16: %
B17: Priced In | C17: -0.08 | D17: -0.03 | E17: 0 | F17: 0.01 | G17: 0.02 | H17: % | I17: Same as Base.
B19: Adjusted gross margin | C19: FY2027E | D19: FY2028E | E19: FY2029E | F19: FY2030E | G19: FY2031E | H19: Units | I19: Source / note
B20: Base | C20: 0.768 | D20: 0.77 | E20: 0.771 | F20: 0.772 | G20: 0.772 | H20: % | I20: FY2026 was 76.6%. Coach is a bigger share of sales, and Coach has the higher margin.
B21: Bull | C21: 0.77 | D21: 0.775 | E21: 0.778 | F21: 0.78 | G21: 0.78 | H21: %
B22: Bear | C22: 0.765 | D22: 0.76 | E22: 0.755 | F22: 0.755 | G22: 0.755 | H22: % | I22: Discounting comes back if demand slows.
B23: Priced In | C23: 0.768 | D23: 0.77 | E23: 0.771 | F23: 0.772 | G23: 0.772 | H23: % | I23: Same as Base.
B25: Adjusted operating margin | C25: FY2027E | D25: FY2028E | E25: FY2029E | F25: FY2030E | G25: FY2031E | H25: Units | I25: Source / note
B26: Base | C26: 0.2385 | D26: 0.242 | E26: 0.244 | F26: 0.245 | G26: 0.245 | H26: % | I26: FY2027 = 23.35% + ~50 bps of guided expansion, then small gains from mix.
B27: Bull | C27: 0.24 | D27: 0.25 | E27: 0.255 | F27: 0.26 | G27: 0.26 | H27: %
B28: Bear | C28: 0.235 | D28: 0.22 | E28: 0.21 | F28: 0.205 | G28: 0.205 | H28: % | I28: Deleverage on fixed store and marketing costs.
B29: Priced In | C29: 0.2385 | D29: 0.242 | E29: 0.244 | F29: 0.245 | G29: 0.245 | H29: % | I29: Same as Base.
B31: Shared Operating Assumptions
B32: Assumption | C32: Value | H32: Units | I32: Source / note
B33: Tax rate on adjusted profit | C33: =ROUND(Historicals!$E$32/(Historicals!$E$29-Historicals!$E$30-Historicals!$E$31),3) -> 0.182 | H33: % | I33: FY2026 adjusted tax rate: $330.0M / $1,812.0M.
B34: D&A incl. cloud computing amortization | C34: =ROUND((Historicals!$E$90+Historicals!$E$91)/Historicals!$E$26,3) -> 0.027 | H34: % of sales | I34: FY2026: ($160.8M + $56.4M) / $7,989.6M.
B35: FY2027 capex and cloud computing | C35: ='Market Data'!$C$21 -> 300 | H35: $M | I35: FY2027 guidance.
B36: Capex and cloud computing after FY2027 | C36: 0.033 | H36: % of sales | I36: My assumption: guidance level as a share of sales (~3.6%), easing as the store refresh slows.
B37: Receivable days | C37: =ROUND(Historicals!$E$66/Historicals!$E$7*365,1) -> 10.8 | H37: days | I37: FY2026 actual.
B38: Inventory days | C38: =ROUND(Historicals!$E$67/(Historicals!$E$26-Historicals!$E$27)*365,1) -> 161.6 | H38: days | I38: FY2026 actual, on adjusted cost of sales.
B39: Payable days | C39: =ROUND(Historicals!$E$75/(Historicals!$E$26-Historicals!$E$27)*365,1) -> 113.9 | H39: days | I39: FY2026 actual.
B40: Accrued liabilities | C40: =ROUND(Historicals!$E$76/Historicals!$E$26,4) -> 0.0945 | H40: % of sales | I40: FY2026 actual.
B41: Stock-based compensation | C41: =ROUND(Historicals!$E$92/Historicals!$E$7,4) -> 0.0131 | H41: % of sales | I41: FY2026 actual. Treated as a real cost in the DCF (not added back).
B42: FY2027 dividend per share | C42: ='Market Data'!$C$23 -> 1.85 | H42: $ | I42: FY2027 guidance ($0.4625 a quarter).
B43: Dividend growth after FY2027 | C43: 0.08 | H43: % | I43: My assumption, in line with earnings growth.
B44: FY2027 share repurchases | C44: ='Market Data'!$C$22 -> 1350 | H44: $M | I44: FY2027 guidance.
B45: Repurchases after FY2027 | C45: Free cash flow less dividends | I45: My assumption: Tapestry keeps returning about all of its free cash flow, as it did in FY2026.
B46: Share price growth used to size buybacks | C46: 0.09 | H46: % / yr | I46: My assumption. Only affects share count and EPS, not the DCF.
B47: New shares issued to employees | C47: 0.015 | H47: % / yr | I47: FY2026: shares fell 7.7M while ~11.5M were repurchased, so ~1.9% were issued. I use 1.5%.
B48: Interest earned on cash | C48: 0.04 | H48: % | I48: My assumption, just under the 1-year Treasury (4.42%).
B49: Terminal growth rate | C49: 0.03 | H49: % | I49: My assumption: inflation plus a little real growth.
B51: Valuation Inputs
B52: Input | C52: Value | H52: Units | I52: Source / note
B53: Share price | C53: ='Market Data'!$C$7 -> 115.82 | H53: $ | I53: Close Oct 8, 2026 (Market Data).
B54: Valuation date | C54: 46303
B55: End of FY2027 | C55: 46571 | I55: FY2027 has 53 weeks, so it ends Saturday, July 3, 2027.
B56: Basic shares outstanding | C56: =Historicals!$C$105 -> 199.39168 | H56: M | I56: July 31, 2026 (10-K cover).
B57: Dilutive securities | C57: =Historicals!$C$106 -> 6.2 | H57: M | I57: FY2026 diluted EPS calculation.
B58: Risk-free rate (10-year Treasury) | C58: ='Market Data'!$C$27 -> 0.0528 | H58: % | I58: Oct 7, 2026.
B59: Beta | C59: ='Market Data'!$C$10 -> 1.43 | H59: x | I59: 5-year beta. Lower betas are tested on the Sensitivity sheet through WACC.
B60: Equity risk premium | C60: ='Market Data'!$C$30 -> 0.0423 | H60: % | I60: Damodaran, January 2026.
B61: Marginal tax rate for debt | C61: 0.21 | H61: % | I61: U.S. federal rate.

Sheet Base
B2: Tapestry Model: Base Case
B3: Income statement, balance sheet, cash flow and DCF. $ in millions except per share. No manual data entry needed.
B5: Income Statement (Adjusted)
B6: FY2026A is pro forma adjusted (excludes Stuart Weitzman and one-time items).
B7: Line | C7: Units | D7: FY2026A | E7: FY2027E | F7: FY2028E | G7: FY2029E | H7: FY2030E | I7: FY2031E | J7: Note
B8: Coach net sales | C8: $M | D8: =Historicals!$E$38 -> 6914.7 | E8: =D8*(1+Inputs!$C$8) -> 7460.9613 | F8: =E8*(1+Inputs!$D$8) -> 7871.3142 | G8: =F8*(1+Inputs!$E$8) -> 8264.8799 | H8: =G8*(1+Inputs!$F$8) -> 8636.7995 | I8: =H8*(1+Inputs!$G$8) -> 8982.2715
B9: Growth | C9: % | D9: =Historicals!$E$38/Historicals!$D$38-1 -> 0.23509869 | E9: =E8/D8-1 -> 0.079 | F9: =F8/E8-1 -> 0.055 | G9: =G8/F8-1 -> 0.05 | H9: =H8/G8-1 -> 0.045 | I9: =I8/H8-1 -> 0.04
B10: Kate Spade net sales | C10: $M | D10: =Historicals!$E$39 -> 1074.9 | E10: =D10*(1+Inputs!$C$14) -> 988.908 | F10: =E10*(1+Inputs!$D$14) -> 959.24076 | G10: =F10*(1+Inputs!$E$14) -> 959.24076 | H10: =G10*(1+Inputs!$F$14) -> 968.83317 | I10: =H10*(1+Inputs!$G$14) -> 988.20983
B11: Growth | C11: % | D11: =Historicals!$E$39/Historicals!$D$39-1 -> -0.10208003 | E11: =E10/D10-1 -> -0.08 | F11: =F10/E10-1 -> -0.03 | G11: =G10/F10-1 -> 0 | H11: =H10/G10-1 -> 0.01 | I11: =I10/H10-1 -> 0.02
B12: Net sales | C12: $M | D12: =D8+D10 -> 7989.6 | E12: =E8+E10 -> 8449.8693 | F12: =F8+F10 -> 8830.5549 | G12: =G8+G10 -> 9224.1206 | H12: =H8+H10 -> 9605.6326 | I12: =I8+I10 -> 9970.4813
B13: Growth | C13: % | E13: =E12/D12-1 -> 0.057608554 | F13: =F12/E12-1 -> 0.045052251 | G13: =G12/F12-1 -> 0.044568627 | H13: =H12/G12-1 -> 0.041360257 | I13: =I12/H12-1 -> 0.037982781
B14: Cost of sales | C14: $M | D14: =D12-D15 -> 1866.5 | E14: =E12-E15 -> 1960.3697 | F14: =F12-F15 -> 2031.0276 | G14: =G12-G15 -> 2112.3236 | H14: =H12-H15 -> 2190.0842 | I14: =I12-I15 -> 2273.2697
B15: Gross profit | C15: $M | D15: =Historicals!$E$27 -> 6123.1 | E15: =E12*Inputs!$C$20 -> 6489.4996 | F15: =F12*Inputs!$D$20 -> 6799.5273 | G15: =G12*Inputs!$E$20 -> 7111.797 | H15: =H12*Inputs!$F$20 -> 7415.5484 | I15: =I12*Inputs!$G$20 -> 7697.2116
B16: Gross margin | C16: % | D16: =D15/D12 -> 0.7663838 | E16: =E15/E12 -> 0.768 | F16: =F15/F12 -> 0.77 | G16: =G15/G12 -> 0.771 | H16: =H15/H12 -> 0.772 | I16: =I15/I12 -> 0.772
B17: SG&A | C17: $M | D17: =Historicals!$E$28 -> 4257.3 | E17: =E15-E19 -> 4474.2058 | F17: =F15-F19 -> 4662.533 | G17: =G15-G19 -> 4861.1116 | H17: =H15-H19 -> 5062.1684 | I17: =I15-I19 -> 5254.4436
B18: % of sales | C18: % | D18: =D17/D12 -> 0.53285521 | E18: =E17/E12 -> 0.5295 | F18: =F17/F12 -> 0.528 | G18: =G17/G12 -> 0.527 | H18: =H17/H12 -> 0.527 | I18: =I17/I12 -> 0.527
B19: Operating income | C19: $M | D19: =Historicals!$E$29 -> 1865.8 | E19: =E12*Inputs!$C$26 -> 2015.2938 | F19: =F12*Inputs!$D$26 -> 2136.9943 | G19: =G12*Inputs!$E$26 -> 2250.6854 | H19: =H12*Inputs!$F$26 -> 2353.38 | I19: =I12*Inputs!$G$26 -> 2442.7679
B20: Operating margin | C20: % | D20: =D19/D12 -> 0.23352859 | E20: =E19/E12 -> 0.2385 | F20: =F19/F12 -> 0.242 | G20: =G19/G12 -> 0.244 | H20: =H19/H12 -> 0.245 | I20: =I19/I12 -> 0.245
B21: Interest expense on senior notes | C21: $M | E21: =Historicals!$D$98*Historicals!$C$98+Historicals!$D$99*Historicals!$C$99+Historicals!$D$100*Historicals!$C$100+Historicals!$D$101*Historicals!$C$101 -> 111.10975 | F21: =Historicals!$D$98*WACC!$C$11+Historicals!$D$99*Historicals!$C$99+Historicals!$D$100*Historicals!$C$100+Historicals!$D$101*Historicals!$C$101 -> 119.53616 | G21: =Historicals!$D$98*WACC!$C$11+Historicals!$D$99*Historicals!$C$99+Historicals!$D$100*Historicals!$C$100+Historicals!$D$101*Historicals!$C$101 -> 119.53616 | H21: =Historicals!$D$98*WACC!$C$11+Historicals!$D$99*Historicals!$C$99+Historicals!$D$100*Historicals!$C$100+Historicals!$D$101*Historicals!$C$101 -> 119.53616 | I21: =Historicals!$D$98*WACC!$C$11+Historicals!$D$99*Historicals!$C$99+Historicals!$D$100*Historicals!$C$100+Historicals!$D$101*Historicals!$C$101 -> 119.53616 | J21: The 2027 notes are refinanced at today's cost of debt from FY2028.
B22: Interest earned on cash | C22: $M | E22: =(D33+D34)*Inputs!$C$48 -> 46.08 | F22: =(E33+E34)*Inputs!$C$48 -> 43.42718 | G22: =(F33+F34)*Inputs!$C$48 -> 43.42718 | H22: =(G33+G34)*Inputs!$C$48 -> 43.42718 | I22: =(H33+H34)*Inputs!$C$48 -> 43.42718 | J22: On cash at the start of the year.
B23: Net interest expense (other income for FY2026A) | C23: $M | D23: =Historicals!$E$30+Historicals!$E$31 -> 53.8 | E23: =E21-E22 -> 65.02975 | F23: =F21-F22 -> 76.108982 | G23: =G21-G22 -> 76.108982 | H23: =H21-H22 -> 76.108982 | I23: =I21-I22 -> 76.108982
B24: Income before taxes | C24: $M | D24: =D19-D23 -> 1812 | E24: =E19-E23 -> 1950.2641 | F24: =F19-F23 -> 2060.8853 | G24: =G19-G23 -> 2174.5765 | H24: =H19-H23 -> 2277.271 | I24: =I19-I23 -> 2366.6589
B25: Income taxes | C25: $M | D25: =Historicals!$E$32 -> 330 | E25: =E24*Inputs!$C$33 -> 354.94806 | F25: =F24*Inputs!$C$33 -> 375.08113 | G25: =G24*Inputs!$C$33 -> 395.77291 | H25: =H24*Inputs!$C$33 -> 414.46332 | I25: =I24*Inputs!$C$33 -> 430.73193
B26: Adjusted net income | C26: $M | D26: =D24-D25 -> 1482 | E26: =E24-E25 -> 1595.316 | F26: =F24-F25 -> 1685.8042 | G26: =G24-G25 -> 1778.8035 | H26: =H24-H25 -> 1862.8077 | I26: =I24-I25 -> 1935.927
B27: Diluted shares (average) | C27: M | D27: =Historicals!$E$20 -> 210.2 | E27: =(D70+E70)/2+Inputs!$C$57 -> 201.25911 | F27: =(E70+F70)/2+Inputs!$C$57 -> 192.87986 | G27: =(F70+G70)/2+Inputs!$C$57 -> 184.8793 | H27: =(G70+H70)/2+Inputs!$C$57 -> 177.10747 | I27: =(H70+I70)/2+Inputs!$C$57 -> 169.65252
B28: Adjusted diluted EPS | C28: $ | D28: =D26/D27 -> 7.0504282 | E28: =E26/E27 -> 7.9266774 | F28: =F26/F27 -> 8.7401774 | G28: =G26/G27 -> 9.6214315 | H28: =H26/H27 -> 10.517951 | I28: =I26/I27 -> 11.41113
B29: Growth | C29: % | E29: =E28/D28-1 -> 0.12428313 | F29: =F28/E28-1 -> 0.10262812 | G29: =G28/F28-1 -> 0.10082795 | H29: =H28/G28-1 -> 0.093179441 | I29: =I28/H28-1 -> 0.084919499
B31: Balance Sheet
B32: Line | C32: Units | D32: FY2026A | E32: FY2027E | F32: FY2028E | G32: FY2029E | H32: FY2030E | I32: FY2031E | J32: Note
B33: Cash and cash equivalents | C33: $M | D33: =Historicals!$E$64 -> 974.7 | E33: =E64 -> 908.37951 | F33: =F64 -> 908.37951 | G33: =G64 -> 908.37951 | H33: =H64 -> 908.37951 | I33: =I64 -> 908.37951
B34: Short-term investments | C34: $M | D34: =Historicals!$E$65 -> 177.3 | E34: =D34 -> 177.3 | F34: =E34 -> 177.3 | G34: =F34 -> 177.3 | H34: =G34 -> 177.3 | I34: =H34 -> 177.3
B35: Trade accounts receivable | C35: $M | D35: =Historicals!$E$66 -> 237.1 | E35: =E12*Inputs!$C$37/365 -> 250.02353 | F35: =F12*Inputs!$C$37/365 -> 261.28765 | G35: =G12*Inputs!$C$37/365 -> 272.93288 | H35: =H12*Inputs!$C$37/365 -> 284.22146 | I35: =I12*Inputs!$C$37/365 -> 295.01698
B36: Inventories | C36: $M | D36: =Historicals!$E$67 -> 826.2 | E36: =E14*Inputs!$C$38/365 -> 867.93353 | F36: =F14*Inputs!$C$38/365 -> 899.21662 | G36: =G14*Inputs!$C$38/365 -> 935.20958 | H36: =H14*Inputs!$C$38/365 -> 969.6373 | I36: =I14*Inputs!$C$38/365 -> 1006.4668
B37: Other current assets | C37: $M | D37: =Historicals!$E$68 -> 667 | E37: =D37 -> 667 | F37: =E37 -> 667 | G37: =F37 -> 667 | H37: =G37 -> 667 | I37: =H37 -> 667
B38: Property, equipment and cloud computing assets | C38: $M | D38: =Historicals!$E$69 -> 502.1 | E38: =D38+E59-E55 -> 573.95353 | F38: =E38+F59-F55 -> 626.93686 | G38: =F38+G59-G55 -> 682.28158 | H38: =G38+H59-H55 -> 739.91538 | I38: =H38+I59-I55 -> 799.73827
B39: Operating lease right-of-use assets | C39: $M | D39: =Historicals!$E$70 -> 1417.2 | E39: =D39 -> 1417.2 | F39: =E39 -> 1417.2 | G39: =F39 -> 1417.2 | H39: =G39 -> 1417.2 | I39: =H39 -> 1417.2
B40: Goodwill and intangibles | C40: $M | D40: =Historicals!$E$71+Historicals!$E$72 -> 1674.2 | E40: =D40 -> 1674.2 | F40: =E40 -> 1674.2 | G40: =F40 -> 1674.2 | H40: =G40 -> 1674.2 | I40: =H40 -> 1674.2
B41: Other assets | C41: $M | D41: =Historicals!$E$73 -> 215.9 | E41: =D41 -> 215.9 | F41: =E41 -> 215.9 | G41: =F41 -> 215.9 | H41: =G41 -> 215.9 | I41: =H41 -> 215.9
B42: Total assets | C42: $M | D42: =SUM(D33:D41) -> 6691.7 | E42: =SUM(E33:E41) -> 6751.8901 | F42: =SUM(F33:F41) -> 6847.4206 | G42: =SUM(G33:G41) -> 6950.4036 | H42: =SUM(H33:H41) -> 7053.7536 | I42: =SUM(I33:I41) -> 7161.2016
B43: Accounts payable | C43: $M | D43: =Historicals!$E$75 -> 582.3 | E43: =E14*Inputs!$C$39/365 -> 611.74276 | F43: =F14*Inputs!$C$39/365 -> 633.79191 | G43: =G14*Inputs!$C$39/365 -> 659.16072 | H43: =H14*Inputs!$C$39/365 -> 683.42629 | I43: =I14*Inputs!$C$39/365 -> 709.38472
B44: Accrued liabilities | C44: $M | D44: =Historicals!$E$76 -> 754.9 | E44: =E12*Inputs!$C$40 -> 798.51265 | F44: =F12*Inputs!$C$40 -> 834.48744 | G44: =G12*Inputs!$C$40 -> 871.6794 | H44: =H12*Inputs!$C$40 -> 907.73228 | I44: =I12*Inputs!$C$40 -> 942.21048
B45: Operating lease liabilities | C45: $M | D45: =Historicals!$E$77+Historicals!$E$80 -> 1574 | E45: =D45 -> 1574 | F45: =E45 -> 1574 | G45: =F45 -> 1574 | H45: =G45 -> 1574 | I45: =H45 -> 1574
B46: Debt | C46: $M | D46: =Historicals!$E$79+Historicals!$E$78 -> 2379 | E46: =D46 -> 2379 | F46: =E46 -> 2379 | G46: =F46 -> 2379 | H46: =G46 -> 2379 | I46: =H46 -> 2379 | J46: Notes are refinanced when they mature.
B47: Other liabilities | C47: $M | D47: =Historicals!$E$81 -> 709.4 | E47: =D47 -> 709.4 | F47: =E47 -> 709.4 | G47: =F47 -> 709.4 | H47: =G47 -> 709.4 | I47: =H47 -> 709.4
B48: Total liabilities | C48: $M | D48: =SUM(D43:D47) -> 5999.6 | E48: =SUM(E43:E47) -> 6072.6554 | F48: =SUM(F43:F47) -> 6130.6794 | G48: =SUM(G43:G47) -> 6193.2401 | H48: =SUM(H43:H47) -> 6253.5586 | I48: =SUM(I43:I47) -> 6313.9952
B49: Stockholders' equity | C49: $M | D49: =Historicals!$E$83 -> 692.1 | E49: =D49+E26+E56-E61-E62 -> 679.2347 | F49: =E49+F26+F56-F61-F62 -> 716.74129 | G49: =F49+G26+G56-G61-G62 -> 757.16345 | H49: =G49+H26+H56-H61-H62 -> 800.19507 | I49: =H49+I26+I56-I61-I62 -> 847.20638
B50: Check: assets less liabilities and equity | C50: $M | D50: =D42-D48-D49 -> 0 | E50: =ROUND(E42-E48-E49,3) -> 0 | F50: =ROUND(F42-F48-F49,3) -> 0 | G50: =ROUND(G42-G48-G49,3) -> 0 | H50: =ROUND(H42-H48-H49,3) -> 0 | I50: =ROUND(I42-I48-I49,3) -> 0 | J50: Should be zero.
B52: Cash Flow Statement
B53: Line | C53: Units | D53: FY2026A | E53: FY2027E | F53: FY2028E | G53: FY2029E | H53: FY2030E | I53: FY2031E | J53: Note
B54: Net income | C54: $M | E54: =E26 -> 1595.316 | F54: =F26 -> 1685.8042 | G54: =G26 -> 1778.8035 | H54: =H26 -> 1862.8077 | I54: =I26 -> 1935.927
B55: Depreciation, amortization and cloud computing amortization | C55: $M | E55: =E12*Inputs!$C$34 -> 228.14647 | F55: =F12*Inputs!$C$34 -> 238.42498 | G55: =G12*Inputs!$C$34 -> 249.05126 | H55: =H12*Inputs!$C$34 -> 259.35208 | I55: =I12*Inputs!$C$34 -> 269.20299
B56: Stock-based compensation | C56: $M | E56: =E12*Inputs!$C$41 -> 110.69329 | F56: =F12*Inputs!$C$41 -> 115.68027 | G56: =G12*Inputs!$C$41 -> 120.83598 | H56: =H12*Inputs!$C$41 -> 125.83379 | I56: =I12*Inputs!$C$41 -> 130.6133
B57: Change in working capital | C57: $M | E57: =-(E35-D35)-(E36-D36)+(E43-D43)+(E44-D44) -> 18.398342 | F57: =-(F35-E35)-(F36-E36)+(F43-E43)+(F44-E44) -> 15.476739 | G57: =-(G35-F35)-(G36-F36)+(G43-F43)+(G44-F44) -> 14.922566 | H57: =-(H35-G35)-(H36-G36)+(H43-G43)+(H44-G44) -> 14.602169 | I57: =-(I35-H35)-(I36-H36)+(I43-H43)+(I44-H44) -> 12.811585
B58: Cash from operations | C58: $M | D58: =Historicals!$E$88 -> 1978.5 | E58: =E54+E55+E56+E57 -> 1952.5541 | F58: =F54+F55+F56+F57 -> 2055.3862 | G58: =G54+G55+G56+G57 -> 2163.6133 | H58: =H54+H55+H56+H57 -> 2262.5957 | I58: =I54+I55+I56+I57 -> 2348.5549
B59: Capex and cloud computing | C59: $M | E59: =Inputs!$C$35 -> 300 | F59: =F12*Inputs!$C$36 -> 291.40831 | G59: =G12*Inputs!$C$36 -> 304.39598 | H59: =H12*Inputs!$C$36 -> 316.98588 | I59: =I12*Inputs!$C$36 -> 329.02588
B60: Free cash flow | C60: $M | E60: =E58-E59 -> 1652.5541 | F60: =F58-F59 -> 1763.9779 | G60: =G58-G59 -> 1859.2174 | H60: =H58-H59 -> 1945.6099 | I60: =I58-I59 -> 2019.529
B61: Dividends | C61: $M | D61: =-Historicals!$E$93 -> 326.1 | E61: =E68*D70 -> 368.8746 | F61: =F68*E70 -> 381.07162 | G61: =G68*F70 -> 394.09319 | H61: =H68*G70 -> 407.19186 | I61: =I68*H70 -> 420.54836
B62: Share repurchases | C62: $M | D62: =-Historicals!$E$94 -> 1554.6 | E62: =Inputs!$C$44 -> 1350 | F62: =MAX(0,F60-F61) -> 1382.9062 | G62: =MAX(0,G60-G61) -> 1465.1242 | H62: =MAX(0,H60-H61) -> 1538.418 | I62: =MAX(0,I60-I61) -> 1598.9806
B63: Change in cash | C63: $M | E63: =E60-E61-E62 -> -66.320488 | F63: =F60-F61-F62 -> 0 | G63: =G60-G61-G62 -> 0 | H63: =H60-H61-H62 -> 0 | I63: =I60-I61-I62 -> 0
B64: Ending cash | C64: $M | E64: =D33+E63 -> 908.37951 | F64: =E33+F63 -> 908.37951 | G64: =F33+G63 -> 908.37951 | H64: =G33+H63 -> 908.37951 | I64: =H33+I63 -> 908.37951
B66: Shares and Dividends
B67: Line | C67: Units | D67: FY2026A | E67: FY2027E | F67: FY2028E | G67: FY2029E | H67: FY2030E | I67: FY2031E | J67: Note
B68: Dividend per share | C68: $ | D68: 1.6 | E68: =Inputs!$C$42 -> 1.85 | F68: =E68*(1+Inputs!$C$43) -> 1.998 | G68: =F68*(1+Inputs!$C$43) -> 2.15784 | H68: =G68*(1+Inputs!$C$43) -> 2.3304672 | I68: =H68*(1+Inputs!$C$43) -> 2.5169046
B69: Average buyback price | C69: $ | E69: =Inputs!$C$53 -> 115.82 | F69: =E69*(1+Inputs!$C$46) -> 126.2438 | G69: =F69*(1+Inputs!$C$46) -> 137.60574 | H69: =G69*(1+Inputs!$C$46) -> 149.99026 | I69: =H69*(1+Inputs!$C$46) -> 163.48938
B70: Basic shares, end of year | C70: M | D70: =Historicals!$C$105 -> 199.39168 | E70: =D70*(1+Inputs!$C$47)-E62/E69 -> 190.72654 | F70: =E70*(1+Inputs!$C$47)-F62/F69 -> 182.63318 | G70: =F70*(1+Inputs!$C$47)-G62/G69 -> 174.72542 | H70: =G70*(1+Inputs!$C$47)-H62/H69 -> 167.08951 | I70: =H70*(1+Inputs!$C$47)-I62/I69 -> 159.81552 | J70: FY2026A column uses the July 31, 2026 count.
B72: Discounted Cash Flow
B73: Unlevered free cash flow. Stock comp is treated as a real cost. Leases stay inside operating costs.
B74: Line | C74: Units | D74: FY2026A | E74: FY2027E | F74: FY2028E | G74: FY2029E | H74: FY2030E | I74: FY2031E | J74: Note
B75: Operating income | C75: $M | E75: =E19 -> 2015.2938 | F75: =F19 -> 2136.9943 | G75: =G19 -> 2250.6854 | H75: =H19 -> 2353.38 | I75: =I19 -> 2442.7679
B76: Taxes on operating income | C76: $M | E76: =-E19*Inputs!$C$33 -> -366.78348 | F76: =-F19*Inputs!$C$33 -> -388.93296 | G76: =-G19*Inputs!$C$33 -> -409.62475 | H76: =-H19*Inputs!$C$33 -> -428.31516 | I76: =-I19*Inputs!$C$33 -> -444.58376
B77: D&A | C77: $M | E77: =E55 -> 228.14647 | F77: =F55 -> 238.42498 | G77: =G55 -> 249.05126 | H77: =H55 -> 259.35208 | I77: =I55 -> 269.20299
B78: Capex and cloud computing | C78: $M | E78: =-E59 -> -300 | F78: =-F59 -> -291.40831 | G78: =-G59 -> -304.39598 | H78: =-H59 -> -316.98588 | I78: =-I59 -> -329.02588
B79: Change in working capital | C79: $M | E79: =E57 -> 18.398342 | F79: =F57 -> 15.476739 | G79: =G57 -> 14.922566 | H79: =H57 -> 14.602169 | I79: =I57 -> 12.811585
B80: Unlevered free cash flow | C80: $M | E80: =SUM(E75:E79) -> 1595.0552 | F80: =SUM(F75:F79) -> 1710.5547 | G80: =SUM(G75:G79) -> 1800.6385 | H80: =SUM(H75:H79) -> 1882.0332 | I80: =SUM(I75:I79) -> 1951.1729
B81: Share of the year still ahead | C81: x | E81: =WACC!$C$28 -> 0.73424658 | F81: =1 -> 1 | G81: =1 -> 1 | H81: =1 -> 1 | I81: =1 -> 1
B82: Cash flow counted | C82: $M | E82: =E80*E81 -> 1171.1638 | F82: =F80*F81 -> 1710.5547 | G82: =G80*G81 -> 1800.6385 | H82: =H80*H81 -> 1882.0332 | I82: =I80*I81 -> 1951.1729
B83: Discount period (mid-year) | C83: years | E83: =WACC!$C$28/2 -> 0.36712329 | F83: =WACC!$C$28+1-0.5 -> 1.2342466 | G83: =WACC!$C$28+2-0.5 -> 2.2342466 | H83: =WACC!$C$28+3-0.5 -> 3.2342466 | I83: =WACC!$C$28+4-0.5 -> 4.2342466
B84: Discount factor | C84: x | E84: =1/(1+WACC!$C$27)^E83 -> 0.9632663 | F84: =1/(1+WACC!$C$27)^F83 -> 0.8817719 | G84: =1/(1+WACC!$C$27)^G83 -> 0.79631207 | H84: =1/(1+WACC!$C$27)^H83 -> 0.71913486 | I84: =1/(1+WACC!$C$27)^I83 -> 0.64943753
B85: Present value | C85: $M | E85: =E82*E84 -> 1128.1426 | F85: =F82*F84 -> 1508.3191 | G85: =G82*G84 -> 1433.8702 | H85: =H82*H84 -> 1353.4357 | I85: =I82*I84 -> 1267.1649
B87: Value per Share
B88: Item | C88: Units | D88: Value | J88: Note
B89: Present value of FY2027 to FY2031 cash flows | C89: $M | D89: =SUM(E85:I85) -> 6690.9325
B90: Terminal value at end of FY2031 | C90: $M | D90: =I80*(1+Inputs!$C$49)/(WACC!$C$27-Inputs!$C$49) -> 25992.245 | J90: Gordon growth.
B91: Present value of terminal value | C91: $M | D91: =D90/(1+WACC!$C$27)^(WACC!$C$28+4) -> 16041.49
B92: Enterprise value | C92: $M | D92: =D89+D91 -> 22732.422
B93: Less: debt | C93: $M | D93: =-Historicals!$E$79 -> -2379 | J93: June 27, 2026.
B94: Plus: cash and short-term investments | C94: $M | D94: =Historicals!$E$64+Historicals!$E$65 -> 1152 | J94: June 27, 2026.
B95: Equity value | C95: $M | D95: =SUM(D92:D94) -> 21505.422
B96: Diluted shares | C96: M | D96: =Inputs!$C$56+Inputs!$C$57 -> 205.59168
B97: Value per share | C97: $ | D97: =D95/D96 -> 104.60259
B98: Upside / (downside) vs today's price | C98: % | D98: =D97/Inputs!$C$53-1 -> -0.096852084
B99: Terminal value as % of enterprise value | C99: % | D99: =D91/D92 -> 0.70566566
B100: Implied exit EV / EBITDA (FY2031) | C100: x | D100: =D90/(I19+I55) -> 9.5842641 | J100: Sanity check on the terminal value.

Sheet Bull
B2: Tapestry Model: Bull Case
B3: Income statement, balance sheet, cash flow and DCF. $ in millions except per share. No manual data entry needed.
B5: Income Statement (Adjusted)
B6: FY2026A is pro forma adjusted (excludes Stuart Weitzman and one-time items).
B7: Line | C7: Units | D7: FY2026A | E7: FY2027E | F7: FY2028E | G7: FY2029E | H7: FY2030E | I7: FY2031E | J7: Note
B8: Coach net sales | C8: $M | D8: =Historicals!$E$38 -> 6914.7 | E8: =D8*(1+Inputs!$C$9) -> 7537.023 | F8: =E8*(1+Inputs!$D$9) -> 8215.3551 | G8: =F8*(1+Inputs!$E$9) -> 8872.5835 | H8: =G8*(1+Inputs!$F$9) -> 9493.6643 | I8: =H8*(1+Inputs!$G$9) -> 10063.284
B9: Growth | C9: % | D9: =Historicals!$E$38/Historicals!$D$38-1 -> 0.23509869 | E9: =E8/D8-1 -> 0.09 | F9: =F8/E8-1 -> 0.09 | G9: =G8/F8-1 -> 0.08 | H9: =H8/G8-1 -> 0.07 | I9: =I8/H8-1 -> 0.06
B10: Kate Spade net sales | C10: $M | D10: =Historicals!$E$39 -> 1074.9 | E10: =D10*(1+Inputs!$C$15) -> 1010.406 | F10: =E10*(1+Inputs!$D$15) -> 1010.406 | G10: =F10*(1+Inputs!$E$15) -> 1030.6141 | H10: =G10*(1+Inputs!$F$15) -> 1061.5325 | I10: =H10*(1+Inputs!$G$15) -> 1093.3785
B11: Growth | C11: % | D11: =Historicals!$E$39/Historicals!$D$39-1 -> -0.10208003 | E11: =E10/D10-1 -> -0.06 | F11: =F10/E10-1 -> 0 | G11: =G10/F10-1 -> 0.02 | H11: =H10/G10-1 -> 0.03 | I11: =I10/H10-1 -> 0.03
B12: Net sales | C12: $M | D12: =D8+D10 -> 7989.6 | E12: =E8+E10 -> 8547.429 | F12: =F8+F10 -> 9225.7611 | G12: =G8+G10 -> 9903.1976 | H12: =H8+H10 -> 10555.197 | I12: =I8+I10 -> 11156.663
B13: Growth | C13: % | E13: =E12/D12-1 -> 0.06981939 | F13: =F12/E12-1 -> 0.079360948 | G13: =G12/F12-1 -> 0.073428796 | H13: =H12/G12-1 -> 0.065837247 | I13: =I12/H12-1 -> 0.05698291
B14: Cost of sales | C14: $M | D14: =D12-D15 -> 1866.5 | E14: =E12-E15 -> 1965.9087 | F14: =F12-F15 -> 2075.7962 | G14: =G12-G15 -> 2198.5099 | H14: =H12-H15 -> 2322.1433 | I14: =I12-I15 -> 2454.4658
B15: Gross profit | C15: $M | D15: =Historicals!$E$27 -> 6123.1 | E15: =E12*Inputs!$C$21 -> 6581.5203 | F15: =F12*Inputs!$D$21 -> 7149.9648 | G15: =G12*Inputs!$E$21 -> 7704.6877 | H15: =H12*Inputs!$F$21 -> 8233.0536 | I15: =I12*Inputs!$G$21 -> 8702.1969
B16: Gross margin | C16: % | D16: =D15/D12 -> 0.7663838 | E16: =E15/E12 -> 0.77 | F16: =F15/F12 -> 0.775 | G16: =G15/G12 -> 0.778 | H16: =H15/H12 -> 0.78 | I16: =I15/I12 -> 0.78
B17: SG&A | C17: $M | D17: =Historicals!$E$28 -> 4257.3 | E17: =E15-E19 -> 4530.1374 | F17: =F15-F19 -> 4843.5246 | G17: =G15-G19 -> 5179.3723 | H17: =H15-H19 -> 5488.7024 | I17: =I15-I19 -> 5801.4646
B18: % of sales | C18: % | D18: =D17/D12 -> 0.53285521 | E18: =E17/E12 -> 0.53 | F18: =F17/F12 -> 0.525 | G18: =G17/G12 -> 0.523 | H18: =H17/H12 -> 0.52 | I18: =I17/I12 -> 0.52
B19: Operating income | C19: $M | D19: =Historicals!$E$29 -> 1865.8 | E19: =E12*Inputs!$C$27 -> 2051.383 | F19: =F12*Inputs!$D$27 -> 2306.4403 | G19: =G12*Inputs!$E$27 -> 2525.3154 | H19: =H12*Inputs!$F$27 -> 2744.3512 | I19: =I12*Inputs!$G$27 -> 2900.7323
B20: Operating margin | C20: % | D20: =D19/D12 -> 0.23352859 | E20: =E19/E12 -> 0.24 | F20: =F19/F12 -> 0.25 | G20: =G19/G12 -> 0.255 | H20: =H19/H12 -> 0.26 | I20: =I19/I12 -> 0.26
B21: Interest expense on senior notes | C21: $M | E21: =Historicals!$D$98*Historicals!$C$98+Historicals!$D$99*Historicals!$C$99+Historicals!$D$100*Historicals!$C$100+Historicals!$D$101*Historicals!$C$101 -> 111.10975 | F21: =Historicals!$D$98*WACC!$C$11+Historicals!$D$99*Historicals!$C$99+Historicals!$D$100*Historicals!$C$100+Historicals!$D$101*Historicals!$C$101 -> 119.53616 | G21: =Historicals!$D$98*WACC!$C$11+Historicals!$D$99*Historicals!$C$99+Historicals!$D$100*Historicals!$C$100+Historicals!$D$101*Historicals!$C$101 -> 119.53616 | H21: =Historicals!$D$98*WACC!$C$11+Historicals!$D$99*Historicals!$C$99+Historicals!$D$100*Historicals!$C$100+Historicals!$D$101*Historicals!$C$101 -> 119.53616 | I21: =Historicals!$D$98*WACC!$C$11+Historicals!$D$99*Historicals!$C$99+Historicals!$D$100*Historicals!$C$100+Historicals!$D$101*Historicals!$C$101 -> 119.53616 | J21: The 2027 notes are refinanced at today's cost of debt from FY2028.
B22: Interest earned on cash | C22: $M | E22: =(D33+D34)*Inputs!$C$48 -> 46.08 | F22: =(E33+E34)*Inputs!$C$48 -> 44.988856 | G22: =(F33+F34)*Inputs!$C$48 -> 44.988856 | H22: =(G33+G34)*Inputs!$C$48 -> 44.988856 | I22: =(H33+H34)*Inputs!$C$48 -> 44.988856 | J22: On cash at the start of the year.
B23: Net interest expense (other income for FY2026A) | C23: $M | D23: =Historicals!$E$30+Historicals!$E$31 -> 53.8 | E23: =E21-E22 -> 65.02975 | F23: =F21-F22 -> 74.547307 | G23: =G21-G22 -> 74.547307 | H23: =H21-H22 -> 74.547307 | I23: =I21-I22 -> 74.547307
B24: Income before taxes | C24: $M | D24: =D19-D23 -> 1812 | E24: =E19-E23 -> 1986.3532 | F24: =F19-F23 -> 2231.893 | G24: =G19-G23 -> 2450.7681 | H24: =H19-H23 -> 2669.8039 | I24: =I19-I23 -> 2826.185
B25: Income taxes | C25: $M | D25: =Historicals!$E$32 -> 330 | E25: =E24*Inputs!$C$33 -> 361.51628 | F25: =F24*Inputs!$C$33 -> 406.20452 | G25: =G24*Inputs!$C$33 -> 446.03979 | H25: =H24*Inputs!$C$33 -> 485.90431 | I25: =I24*Inputs!$C$33 -> 514.36567
B26: Adjusted net income | C26: $M | D26: =D24-D25 -> 1482 | E26: =E24-E25 -> 1624.8369 | F26: =F24-F25 -> 1825.6884 | G26: =G24-G25 -> 2004.7283 | H26: =H24-H25 -> 2183.8996 | I26: =I24-I25 -> 2311.8193
B27: Diluted shares (average) | C27: M | D27: =Historicals!$E$20 -> 210.2 | E27: =(D70+E70)/2+Inputs!$C$57 -> 201.25911 | F27: =(E70+F70)/2+Inputs!$C$57 -> 192.25851 | G27: =(F70+G70)/2+Inputs!$C$57 -> 182.73181 | H27: =(G70+H70)/2+Inputs!$C$57 -> 172.8772 | I27: =(H70+I70)/2+Inputs!$C$57 -> 162.95937
B28: Adjusted diluted EPS | C28: $ | D28: =D26/D27 -> 7.0504282 | E28: =E26/E27 -> 8.0733585 | F28: =F26/F27 -> 9.4960087 | G28: =G26/G27 -> 10.970877 | H28: =H26/H27 -> 12.632664 | I28: =I26/I27 -> 14.186476
B29: Growth | C29: % | E29: =E28/D28-1 -> 0.14508769 | F29: =F28/E28-1 -> 0.17621541 | G29: =G28/F28-1 -> 0.15531458 | H29: =H28/G28-1 -> 0.15147256 | I29: =I28/H28-1 -> 0.12299957
B31: Balance Sheet
B32: Line | C32: Units | D32: FY2026A | E32: FY2027E | F32: FY2028E | G32: FY2029E | H32: FY2030E | I32: FY2031E | J32: Note
B33: Cash and cash equivalents | C33: $M | D33: =Historicals!$E$64 -> 974.7 | E33: =E64 -> 947.4214 | F33: =F64 -> 947.4214 | G33: =G64 -> 947.4214 | H33: =H64 -> 947.4214 | I33: =I64 -> 947.4214
B34: Short-term investments | C34: $M | D34: =Historicals!$E$65 -> 177.3 | E34: =D34 -> 177.3 | F34: =E34 -> 177.3 | G34: =F34 -> 177.3 | H34: =G34 -> 177.3 | I34: =H34 -> 177.3
B35: Trade accounts receivable | C35: $M | D35: =Historicals!$E$66 -> 237.1 | E35: =E12*Inputs!$C$37/365 -> 252.91023 | F35: =F12*Inputs!$C$37/365 -> 272.98142 | G35: =G12*Inputs!$C$37/365 -> 293.02612 | H35: =H12*Inputs!$C$37/365 -> 312.31815 | I35: =I12*Inputs!$C$37/365 -> 330.11495
B36: Inventories | C36: $M | D36: =Historicals!$E$67 -> 826.2 | E36: =E14*Inputs!$C$38/365 -> 870.38587 | F36: =F14*Inputs!$C$38/365 -> 919.03746 | G36: =G14*Inputs!$C$38/365 -> 973.36766 | H36: =H14*Inputs!$C$38/365 -> 1028.1051 | I36: =I14*Inputs!$C$38/365 -> 1086.6895
B37: Other current assets | C37: $M | D37: =Historicals!$E$68 -> 667 | E37: =D37 -> 667 | F37: =E37 -> 667 | G37: =F37 -> 667 | H37: =G37 -> 667 | I37: =H37 -> 667
B38: Property, equipment and cloud computing assets | C38: $M | D38: =Historicals!$E$69 -> 502.1 | E38: =D38+E59-E55 -> 571.31942 | F38: =E38+F59-F55 -> 626.67398 | G38: =F38+G59-G55 -> 686.09317 | H38: =G38+H59-H55 -> 749.42435 | I38: =H38+I59-I55 -> 816.36433
B39: Operating lease right-of-use assets | C39: $M | D39: =Historicals!$E$70 -> 1417.2 | E39: =D39 -> 1417.2 | F39: =E39 -> 1417.2 | G39: =F39 -> 1417.2 | H39: =G39 -> 1417.2 | I39: =H39 -> 1417.2
B40: Goodwill and intangibles | C40: $M | D40: =Historicals!$E$71+Historicals!$E$72 -> 1674.2 | E40: =D40 -> 1674.2 | F40: =E40 -> 1674.2 | G40: =F40 -> 1674.2 | H40: =G40 -> 1674.2 | I40: =H40 -> 1674.2
B41: Other assets | C41: $M | D41: =Historicals!$E$73 -> 215.9 | E41: =D41 -> 215.9 | F41: =E41 -> 215.9 | G41: =F41 -> 215.9 | H41: =G41 -> 215.9 | I41: =H41 -> 215.9
B42: Total assets | C42: $M | D42: =SUM(D33:D41) -> 6691.7 | E42: =SUM(E33:E41) -> 6793.6369 | F42: =SUM(F33:F41) -> 6917.7143 | G42: =SUM(G33:G41) -> 7051.5083 | H42: =SUM(H33:H41) -> 7188.869 | I42: =SUM(I33:I41) -> 7332.1902
B43: Accounts payable | C43: $M | D43: =Historicals!$E$75 -> 582.3 | E43: =E14*Inputs!$C$39/365 -> 613.47123 | F43: =F14*Inputs!$C$39/365 -> 647.76217 | G43: =G14*Inputs!$C$39/365 -> 686.05554 | H43: =H14*Inputs!$C$39/365 -> 724.63595 | I43: =I14*Inputs!$C$39/365 -> 765.92782
B44: Accrued liabilities | C44: $M | D44: =Historicals!$E$76 -> 754.9 | E44: =E12*Inputs!$C$40 -> 807.73204 | F44: =F12*Inputs!$C$40 -> 871.83442 | G44: =G12*Inputs!$C$40 -> 935.85217 | H44: =H12*Inputs!$C$40 -> 997.4661 | I44: =I12*Inputs!$C$40 -> 1054.3046
B45: Operating lease liabilities | C45: $M | D45: =Historicals!$E$77+Historicals!$E$80 -> 1574 | E45: =D45 -> 1574 | F45: =E45 -> 1574 | G45: =F45 -> 1574 | H45: =G45 -> 1574 | I45: =H45 -> 1574
B46: Debt | C46: $M | D46: =Historicals!$E$79+Historicals!$E$78 -> 2379 | E46: =D46 -> 2379 | F46: =E46 -> 2379 | G46: =F46 -> 2379 | H46: =G46 -> 2379 | I46: =H46 -> 2379 | J46: Notes are refinanced when they mature.
B47: Other liabilities | C47: $M | D47: =Historicals!$E$81 -> 709.4 | E47: =D47 -> 709.4 | F47: =E47 -> 709.4 | G47: =F47 -> 709.4 | H47: =G47 -> 709.4 | I47: =H47 -> 709.4
B48: Total liabilities | C48: $M | D48: =SUM(D43:D47) -> 5999.6 | E48: =SUM(E43:E47) -> 6083.6033 | F48: =SUM(F43:F47) -> 6181.9966 | G48: =SUM(G43:G47) -> 6284.3077 | H48: =SUM(H43:H47) -> 6384.5021 | I48: =SUM(I43:I47) -> 6482.6324
B49: Stockholders' equity | C49: $M | D49: =Historicals!$E$83 -> 692.1 | E49: =D49+E26+E56-E61-E62 -> 710.03364 | F49: =E49+F26+F56-F61-F62 -> 735.71767 | G49: =F49+G26+G56-G61-G62 -> 767.20063 | H49: =G49+H26+H56-H61-H62 -> 804.36694 | I49: =H49+I26+I56-I61-I62 -> 849.55774
B50: Check: assets less liabilities and equity | C50: $M | D50: =D42-D48-D49 -> 0 | E50: =ROUND(E42-E48-E49,3) -> 0 | F50: =ROUND(F42-F48-F49,3) -> 0 | G50: =ROUND(G42-G48-G49,3) -> 0 | H50: =ROUND(H42-H48-H49,3) -> 0 | I50: =ROUND(I42-I48-I49,3) -> 0 | J50: Should be zero.
B52: Cash Flow Statement
B53: Line | C53: Units | D53: FY2026A | E53: FY2027E | F53: FY2028E | G53: FY2029E | H53: FY2030E | I53: FY2031E | J53: Note
B54: Net income | C54: $M | E54: =E26 -> 1624.8369 | F54: =F26 -> 1825.6884 | G54: =G26 -> 2004.7283 | H54: =H26 -> 2183.8996 | I54: =I26 -> 2311.8193
B55: Depreciation, amortization and cloud computing amortization | C55: $M | E55: =E12*Inputs!$C$34 -> 230.78058 | F55: =F12*Inputs!$C$34 -> 249.09555 | G55: =G12*Inputs!$C$34 -> 267.38634 | H55: =H12*Inputs!$C$34 -> 284.99032 | I55: =I12*Inputs!$C$34 -> 301.22989
B56: Stock-based compensation | C56: $M | E56: =E12*Inputs!$C$41 -> 111.97132 | F56: =F12*Inputs!$C$41 -> 120.85747 | G56: =G12*Inputs!$C$41 -> 129.73189 | H56: =H12*Inputs!$C$41 -> 138.27308 | I56: =I12*Inputs!$C$41 -> 146.15228
B57: Change in working capital | C57: $M | E57: =-(E35-D35)-(E36-D36)+(E43-D43)+(E44-D44) -> 24.007173 | F57: =-(F35-E35)-(F36-E36)+(F43-E43)+(F44-E44) -> 29.670535 | G57: =-(G35-F35)-(G36-F36)+(G43-F43)+(G44-F44) -> 27.936233 | H57: =-(H35-G35)-(H36-G36)+(H43-G43)+(H44-G44) -> 26.16487 | I57: =-(I35-H35)-(I36-H36)+(I43-H43)+(I44-H44) -> 21.749169
B58: Cash from operations | C58: $M | D58: =Historicals!$E$88 -> 1978.5 | E58: =E54+E55+E56+E57 -> 1991.596 | F58: =F54+F55+F56+F57 -> 2225.312 | G58: =G54+G55+G56+G57 -> 2429.7827 | H58: =H54+H55+H56+H57 -> 2633.3278 | I58: =I54+I55+I56+I57 -> 2780.9507
B59: Capex and cloud computing | C59: $M | E59: =Inputs!$C$35 -> 300 | F59: =F12*Inputs!$C$36 -> 304.45012 | G59: =G12*Inputs!$C$36 -> 326.80552 | H59: =H12*Inputs!$C$36 -> 348.3215 | I59: =I12*Inputs!$C$36 -> 368.16987
B60: Free cash flow | C60: $M | E60: =E58-E59 -> 1691.596 | F60: =F58-F59 -> 1920.8619 | G60: =G58-G59 -> 2102.9772 | H60: =H58-H59 -> 2285.0063 | I60: =I58-I59 -> 2412.7808
B61: Dividends | C61: $M | D61: =-Historicals!$E$93 -> 326.1 | E61: =E68*D70 -> 368.8746 | F61: =F68*E70 -> 381.07162 | G61: =G68*F70 -> 391.41162 | H61: =H68*G70 -> 400.07864 | I61: =I68*H70 -> 406.93627
B62: Share repurchases | C62: $M | D62: =-Historicals!$E$94 -> 1554.6 | E62: =Inputs!$C$44 -> 1350 | F62: =MAX(0,F60-F61) -> 1539.7903 | G62: =MAX(0,G60-G61) -> 1711.5656 | H62: =MAX(0,H60-H61) -> 1884.9277 | I62: =MAX(0,I60-I61) -> 2005.8445
B63: Change in cash | C63: $M | E63: =E60-E61-E62 -> -27.278603 | F63: =F60-F61-F62 -> 0 | G63: =G60-G61-G62 -> 0 | H63: =H60-H61-H62 -> 0 | I63: =I60-I61-I62 -> 0
B64: Ending cash | C64: $M | E64: =D33+E63 -> 947.4214 | F64: =E33+F63 -> 947.4214 | G64: =F33+G63 -> 947.4214 | H64: =G33+H63 -> 947.4214 | I64: =H33+I63 -> 947.4214
B66: Shares and Dividends
B67: Line | C67: Units | D67: FY2026A | E67: FY2027E | F67: FY2028E | G67: FY2029E | H67: FY2030E | I67: FY2031E | J67: Note
B68: Dividend per share | C68: $ | D68: 1.6 | E68: =Inputs!$C$42 -> 1.85 | F68: =E68*(1+Inputs!$C$43) -> 1.998 | G68: =F68*(1+Inputs!$C$43) -> 2.15784 | H68: =G68*(1+Inputs!$C$43) -> 2.3304672 | I68: =H68*(1+Inputs!$C$43) -> 2.5169046
B69: Average buyback price | C69: $ | E69: =Inputs!$C$53 -> 115.82 | F69: =E69*(1+Inputs!$C$46) -> 126.2438 | G69: =F69*(1+Inputs!$C$46) -> 137.60574 | H69: =G69*(1+Inputs!$C$46) -> 149.99026 | I69: =H69*(1+Inputs!$C$46) -> 163.48938
B70: Basic shares, end of year | C70: M | D70: =Historicals!$C$105 -> 199.39168 | E70: =D70*(1+Inputs!$C$47)-E62/E69 -> 190.72654 | F70: =E70*(1+Inputs!$C$47)-F62/F69 -> 181.39048 | G70: =F70*(1+Inputs!$C$47)-G62/G69 -> 171.67315 | H70: =G70*(1+Inputs!$C$47)-H62/H69 -> 161.68124 | I70: =H70*(1+Inputs!$C$47)-I62/I69 -> 151.8375 | J70: FY2026A column uses the July 31, 2026 count.
B72: Discounted Cash Flow
B73: Unlevered free cash flow. Stock comp is treated as a real cost. Leases stay inside operating costs.
B74: Line | C74: Units | D74: FY2026A | E74: FY2027E | F74: FY2028E | G74: FY2029E | H74: FY2030E | I74: FY2031E | J74: Note
B75: Operating income | C75: $M | E75: =E19 -> 2051.383 | F75: =F19 -> 2306.4403 | G75: =G19 -> 2525.3154 | H75: =H19 -> 2744.3512 | I75: =I19 -> 2900.7323
B76: Taxes on operating income | C76: $M | E76: =-E19*Inputs!$C$33 -> -373.3517 | F76: =-F19*Inputs!$C$33 -> -419.77213 | G76: =-G19*Inputs!$C$33 -> -459.6074 | H76: =-H19*Inputs!$C$33 -> -499.47192 | I76: =-I19*Inputs!$C$33 -> -527.93328
B77: D&A | C77: $M | E77: =E55 -> 230.78058 | F77: =F55 -> 249.09555 | G77: =G55 -> 267.38634 | H77: =H55 -> 284.99032 | I77: =I55 -> 301.22989
B78: Capex and cloud computing | C78: $M | E78: =-E59 -> -300 | F78: =-F59 -> -304.45012 | G78: =-G59 -> -326.80552 | H78: =-H59 -> -348.3215 | I78: =-I59 -> -368.16987
B79: Change in working capital | C79: $M | E79: =E57 -> 24.007173 | F79: =F57 -> 29.670535 | G79: =G57 -> 27.936233 | H79: =H57 -> 26.16487 | I79: =I57 -> 21.749169
B80: Unlevered free cash flow | C80: $M | E80: =SUM(E75:E79) -> 1632.819 | F80: =SUM(F75:F79) -> 1860.9841 | G80: =SUM(G75:G79) -> 2034.225 | H80: =SUM(H75:H79) -> 2207.713 | I80: =SUM(I75:I79) -> 2327.6082
B81: Share of the year still ahead | C81: x | E81: =WACC!$C$28 -> 0.73424658 | F81: =1 -> 1 | G81: =1 -> 1 | H81: =1 -> 1 | I81: =1 -> 1
B82: Cash flow counted | C82: $M | E82: =E80*E81 -> 1198.8918 | F82: =F80*F81 -> 1860.9841 | G82: =G80*G81 -> 2034.225 | H82: =H80*H81 -> 2207.713 | I82: =I80*I81 -> 2327.6082
B83: Discount period (mid-year) | C83: years | E83: =WACC!$C$28/2 -> 0.36712329 | F83: =WACC!$C$28+1-0.5 -> 1.2342466 | G83: =WACC!$C$28+2-0.5 -> 2.2342466 | H83: =WACC!$C$28+3-0.5 -> 3.2342466 | I83: =WACC!$C$28+4-0.5 -> 4.2342466
B84: Discount factor | C84: x | E84: =1/(1+WACC!$C$27)^E83 -> 0.9632663 | F84: =1/(1+WACC!$C$27)^F83 -> 0.8817719 | G84: =1/(1+WACC!$C$27)^G83 -> 0.79631207 | H84: =1/(1+WACC!$C$27)^H83 -> 0.71913486 | I84: =1/(1+WACC!$C$27)^I83 -> 0.64943753
B85: Present value | C85: $M | E85: =E82*E84 -> 1154.852 | F85: =F82*F84 -> 1640.9635 | G85: =G82*G84 -> 1619.8779 | H85: =H82*H84 -> 1587.6433 | I85: =I82*I84 -> 1511.6361
B87: Value per Share
B88: Item | C88: Units | D88: Value | J88: Note
B89: Present value of FY2027 to FY2031 cash flows | C89: $M | D89: =SUM(E85:I85) -> 7514.9729
B90: Terminal value at end of FY2031 | C90: $M | D90: =I80*(1+Inputs!$C$49)/(WACC!$C$27-Inputs!$C$49) -> 31006.87 | J90: Gordon growth.
B91: Present value of terminal value | C91: $M | D91: =D90/(1+WACC!$C$27)^(WACC!$C$28+4) -> 19136.338
B92: Enterprise value | C92: $M | D92: =D89+D91 -> 26651.311
B93: Less: debt | C93: $M | D93: =-Historicals!$E$79 -> -2379 | J93: June 27, 2026.
B94: Plus: cash and short-term investments | C94: $M | D94: =Historicals!$E$64+Historicals!$E$65 -> 1152 | J94: June 27, 2026.
B95: Equity value | C95: $M | D95: =SUM(D92:D94) -> 25424.311
B96: Diluted shares | C96: M | D96: =Inputs!$C$56+Inputs!$C$57 -> 205.59168
B97: Value per share | C97: $ | D97: =D95/D96 -> 123.66411
B98: Upside / (downside) vs today's price | C98: % | D98: =D97/Inputs!$C$53-1 -> 0.067726701
B99: Terminal value as % of enterprise value | C99: % | D99: =D91/D92 -> 0.71802615
B100: Implied exit EV / EBITDA (FY2031) | C100: x | D100: =D90/(I19+I55) -> 9.6837091 | J100: Sanity check on the terminal value.

Sheet Bear
B2: Tapestry Model: Bear Case
B3: Income statement, balance sheet, cash flow and DCF. $ in millions except per share. No manual data entry needed.
B5: Income Statement (Adjusted)
B6: FY2026A is pro forma adjusted (excludes Stuart Weitzman and one-time items).
B7: Line | C7: Units | D7: FY2026A | E7: FY2027E | F7: FY2028E | G7: FY2029E | H7: FY2030E | I7: FY2031E | J7: Note
B8: Coach net sales | C8: $M | D8: =Historicals!$E$38 -> 6914.7 | E8: =D8*(1+Inputs!$C$10) -> 7329.582 | F8: =E8*(1+Inputs!$D$10) -> 7329.582 | G8: =F8*(1+Inputs!$E$10) -> 7182.9904 | H8: =G8*(1+Inputs!$F$10) -> 7254.8203 | I8: =H8*(1+Inputs!$G$10) -> 7399.9167
B9: Growth | C9: % | D9: =Historicals!$E$38/Historicals!$D$38-1 -> 0.23509869 | E9: =E8/D8-1 -> 0.06 | F9: =F8/E8-1 -> 0 | G9: =G8/F8-1 -> -0.02 | H9: =H8/G8-1 -> 0.01 | I9: =I8/H8-1 -> 0.02
B10: Kate Spade net sales | C10: $M | D10: =Historicals!$E$39 -> 1074.9 | E10: =D10*(1+Inputs!$C$16) -> 967.41 | F10: =E10*(1+Inputs!$D$16) -> 909.3654 | G10: =F10*(1+Inputs!$E$16) -> 882.08444 | H10: =G10*(1+Inputs!$F$16) -> 882.08444 | I10: =H10*(1+Inputs!$G$16) -> 890.90528
B11: Growth | C11: % | D11: =Historicals!$E$39/Historicals!$D$39-1 -> -0.10208003 | E11: =E10/D10-1 -> -0.1 | F11: =F10/E10-1 -> -0.06 | G11: =G10/F10-1 -> -0.03 | H11: =H10/G10-1 -> 0 | I11: =I10/H10-1 -> 0.01
B12: Net sales | C12: $M | D12: =D8+D10 -> 7989.6 | E12: =E8+E10 -> 8296.992 | F12: =F8+F10 -> 8238.9474 | G12: =G8+G10 -> 8065.0748 | H12: =H8+H10 -> 8136.9047 | I12: =I8+I10 -> 8290.822
B13: Growth | C13: % | E13: =E12/D12-1 -> 0.038474016 | F13: =F12/E12-1 -> -0.0069958607 | G13: =G12/F12-1 -> -0.02110374 | H13: =H12/G12-1 -> 0.0089062911 | I13: =I12/H12-1 -> 0.018915946
B14: Cost of sales | C14: $M | D14: =D12-D15 -> 1866.5 | E14: =E12-E15 -> 1949.7931 | F14: =F12-F15 -> 1977.3474 | G14: =G12-G15 -> 1975.9433 | H14: =H12-H15 -> 1993.5417 | I14: =I12-I15 -> 2031.2514
B15: Gross profit | C15: $M | D15: =Historicals!$E$27 -> 6123.1 | E15: =E12*Inputs!$C$22 -> 6347.1989 | F15: =F12*Inputs!$D$22 -> 6261.6 | G15: =G12*Inputs!$E$22 -> 6089.1315 | H15: =H12*Inputs!$F$22 -> 6143.363 | I15: =I12*Inputs!$G$22 -> 6259.5706
B16: Gross margin | C16: % | D16: =D15/D12 -> 0.7663838 | E16: =E15/E12 -> 0.765 | F16: =F15/F12 -> 0.76 | G16: =G15/G12 -> 0.755 | H16: =H15/H12 -> 0.755 | I16: =I15/I12 -> 0.755
B17: SG&A | C17: $M | D17: =Historicals!$E$28 -> 4257.3 | E17: =E15-E19 -> 4397.4058 | F17: =F15-F19 -> 4449.0316 | G17: =G15-G19 -> 4395.4658 | H17: =H15-H19 -> 4475.2976 | I17: =I15-I19 -> 4559.9521
B18: % of sales | C18: % | D18: =D17/D12 -> 0.53285521 | E18: =E17/E12 -> 0.53 | F18: =F17/F12 -> 0.54 | G18: =G17/G12 -> 0.545 | H18: =H17/H12 -> 0.55 | I18: =I17/I12 -> 0.55
B19: Operating income | C19: $M | D19: =Historicals!$E$29 -> 1865.8 | E19: =E12*Inputs!$C$28 -> 1949.7931 | F19: =F12*Inputs!$D$28 -> 1812.5684 | G19: =G12*Inputs!$E$28 -> 1693.6657 | H19: =H12*Inputs!$F$28 -> 1668.0655 | I19: =I12*Inputs!$G$28 -> 1699.6185
B20: Operating margin | C20: % | D20: =D19/D12 -> 0.23352859 | E20: =E19/E12 -> 0.235 | F20: =F19/F12 -> 0.22 | G20: =G19/G12 -> 0.21 | H20: =H19/H12 -> 0.205 | I20: =I19/I12 -> 0.205
B21: Interest expense on senior notes | C21: $M | E21: =Historicals!$D$98*Historicals!$C$98+Historicals!$D$99*Historicals!$C$99+Historicals!$D$100*Historicals!$C$100+Historicals!$D$101*Historicals!$C$101 -> 111.10975 | F21: =Historicals!$D$98*WACC!$C$11+Historicals!$D$99*Historicals!$C$99+Historicals!$D$100*Historicals!$C$100+Historicals!$D$101*Historicals!$C$101 -> 119.53616 | G21: =Historicals!$D$98*WACC!$C$11+Historicals!$D$99*Historicals!$C$99+Historicals!$D$100*Historicals!$C$100+Historicals!$D$101*Historicals!$C$101 -> 119.53616 | H21: =Historicals!$D$98*WACC!$C$11+Historicals!$D$99*Historicals!$C$99+Historicals!$D$100*Historicals!$C$100+Historicals!$D$101*Historicals!$C$101 -> 119.53616 | I21: =Historicals!$D$98*WACC!$C$11+Historicals!$D$99*Historicals!$C$99+Historicals!$D$100*Historicals!$C$100+Historicals!$D$101*Historicals!$C$101 -> 119.53616 | J21: The 2027 notes are refinanced at today's cost of debt from FY2028.
B22: Interest earned on cash | C22: $M | E22: =(D33+D34)*Inputs!$C$48 -> 46.08 | F22: =(E33+E34)*Inputs!$C$48 -> 40.697134 | G22: =(F33+F34)*Inputs!$C$48 -> 40.697134 | H22: =(G33+G34)*Inputs!$C$48 -> 40.697134 | I22: =(H33+H34)*Inputs!$C$48 -> 40.697134 | J22: On cash at the start of the year.
B23: Net interest expense (other income for FY2026A) | C23: $M | D23: =Historicals!$E$30+Historicals!$E$31 -> 53.8 | E23: =E21-E22 -> 65.02975 | F23: =F21-F22 -> 78.839029 | G23: =G21-G22 -> 78.839029 | H23: =H21-H22 -> 78.839029 | I23: =I21-I22 -> 78.839029
B24: Income before taxes | C24: $M | D24: =D19-D23 -> 1812 | E24: =E19-E23 -> 1884.7634 | F24: =F19-F23 -> 1733.7294 | G24: =G19-G23 -> 1614.8267 | H24: =H19-H23 -> 1589.2264 | I24: =I19-I23 -> 1620.7795
B25: Income taxes | C25: $M | D25: =Historicals!$E$32 -> 330 | E25: =E24*Inputs!$C$33 -> 343.02693 | F25: =F24*Inputs!$C$33 -> 315.53875 | G25: =G24*Inputs!$C$33 -> 293.89846 | H25: =H24*Inputs!$C$33 -> 289.23921 | I25: =I24*Inputs!$C$33 -> 294.98186
B26: Adjusted net income | C26: $M | D26: =D24-D25 -> 1482 | E26: =E24-E25 -> 1541.7364 | F26: =F24-F25 -> 1418.1906 | G26: =G24-G25 -> 1320.9282 | H26: =H24-H25 -> 1299.9872 | I26: =I24-I25 -> 1325.7976
B27: Diluted shares (average) | C27: M | D27: =Historicals!$E$20 -> 210.2 | E27: =(D70+E70)/2+Inputs!$C$57 -> 201.25911 | F27: =(E70+F70)/2+Inputs!$C$57 -> 194.04688 | G27: =(F70+G70)/2+Inputs!$C$57 -> 189.03734 | H27: =(G70+H70)/2+Inputs!$C$57 -> 185.1326 | I27: =(H70+I70)/2+Inputs!$C$57 -> 181.79988
B28: Adjusted diluted EPS | C28: $ | D28: =D26/D27 -> 7.0504282 | E28: =E26/E27 -> 7.6604555 | F28: =F26/F27 -> 7.3084948 | G28: =G26/G27 -> 6.9876575 | H28: =H26/H27 -> 7.0219251 | I28: =I26/I27 -> 7.2926209
B29: Growth | C29: % | E29: =E28/D28-1 -> 0.08652345 | F29: =F28/E28-1 -> -0.045945139 | G29: =G28/F28-1 -> -0.043899234 | H29: =H28/G28-1 -> 0.0049040166 | I29: =I28/H28-1 -> 0.038550078
B31: Balance Sheet
B32: Line | C32: Units | D32: FY2026A | E32: FY2027E | F32: FY2028E | G32: FY2029E | H32: FY2030E | I32: FY2031E | J32: Note
B33: Cash and cash equivalents | C33: $M | D33: =Historicals!$E$64 -> 974.7 | E33: =E64 -> 840.12834 | F33: =F64 -> 840.12834 | G33: =G64 -> 840.12834 | H33: =H64 -> 840.12834 | I33: =I64 -> 840.12834
B34: Short-term investments | C34: $M | D34: =Historicals!$E$65 -> 177.3 | E34: =D34 -> 177.3 | F34: =E34 -> 177.3 | G34: =F34 -> 177.3 | H34: =G34 -> 177.3 | I34: =H34 -> 177.3
B35: Trade accounts receivable | C35: $M | D35: =Historicals!$E$66 -> 237.1 | E35: =E12*Inputs!$C$37/365 -> 245.50004 | F35: =F12*Inputs!$C$37/365 -> 243.78255 | G35: =G12*Inputs!$C$37/365 -> 238.63783 | H35: =H12*Inputs!$C$37/365 -> 240.76321 | I35: =I12*Inputs!$C$37/365 -> 245.31747
B36: Inventories | C36: $M | D36: =Historicals!$E$67 -> 826.2 | E36: =E14*Inputs!$C$38/365 -> 863.25087 | F36: =F14*Inputs!$C$38/365 -> 875.45024 | G36: =G14*Inputs!$C$38/365 -> 874.82861 | H36: =H14*Inputs!$C$38/365 -> 882.62008 | I36: =I14*Inputs!$C$38/365 -> 899.31568
B37: Other current assets | C37: $M | D37: =Historicals!$E$68 -> 667 | E37: =D37 -> 667 | F37: =E37 -> 667 | G37: =F37 -> 667 | H37: =G37 -> 667 | I37: =H37 -> 667
B38: Property, equipment and cloud computing assets | C38: $M | D38: =Historicals!$E$69 -> 502.1 | E38: =D38+E59-E55 -> 578.08122 | F38: =E38+F59-F55 -> 627.5149 | G38: =F38+G59-G55 -> 675.90535 | H38: =G38+H59-H55 -> 724.72678 | I38: =H38+I59-I55 -> 774.47171
B39: Operating lease right-of-use assets | C39: $M | D39: =Historicals!$E$70 -> 1417.2 | E39: =D39 -> 1417.2 | F39: =E39 -> 1417.2 | G39: =F39 -> 1417.2 | H39: =G39 -> 1417.2 | I39: =H39 -> 1417.2
B40: Goodwill and intangibles | C40: $M | D40: =Historicals!$E$71+Historicals!$E$72 -> 1674.2 | E40: =D40 -> 1674.2 | F40: =E40 -> 1674.2 | G40: =F40 -> 1674.2 | H40: =G40 -> 1674.2 | I40: =H40 -> 1674.2
B41: Other assets | C41: $M | D41: =Historicals!$E$73 -> 215.9 | E41: =D41 -> 215.9 | F41: =E41 -> 215.9 | G41: =F41 -> 215.9 | H41: =G41 -> 215.9 | I41: =H41 -> 215.9
B42: Total assets | C42: $M | D42: =SUM(D33:D41) -> 6691.7 | E42: =SUM(E33:E41) -> 6678.5605 | F42: =SUM(F33:F41) -> 6738.476 | G42: =SUM(G33:G41) -> 6781.1001 | H42: =SUM(H33:H41) -> 6839.8384 | I42: =SUM(I33:I41) -> 6910.8332
B43: Accounts payable | C43: $M | D43: =Historicals!$E$75 -> 582.3 | E43: =E14*Inputs!$C$39/365 -> 608.44229 | F43: =F14*Inputs!$C$39/365 -> 617.04073 | G43: =G14*Inputs!$C$39/365 -> 616.60259 | H43: =H14*Inputs!$C$39/365 -> 622.09423 | I43: =I14*Inputs!$C$39/365 -> 633.86173
B44: Accrued liabilities | C44: $M | D44: =Historicals!$E$76 -> 754.9 | E44: =E12*Inputs!$C$40 -> 784.06574 | F44: =F12*Inputs!$C$40 -> 778.58053 | G44: =G12*Inputs!$C$40 -> 762.14957 | H44: =H12*Inputs!$C$40 -> 768.93749 | I44: =I12*Inputs!$C$40 -> 783.48267
B45: Operating lease liabilities | C45: $M | D45: =Historicals!$E$77+Historicals!$E$80 -> 1574 | E45: =D45 -> 1574 | F45: =E45 -> 1574 | G45: =F45 -> 1574 | H45: =G45 -> 1574 | I45: =H45 -> 1574
B46: Debt | C46: $M | D46: =Historicals!$E$79+Historicals!$E$78 -> 2379 | E46: =D46 -> 2379 | F46: =E46 -> 2379 | G46: =F46 -> 2379 | H46: =G46 -> 2379 | I46: =H46 -> 2379 | J46: Notes are refinanced when they mature.
B47: Other liabilities | C47: $M | D47: =Historicals!$E$81 -> 709.4 | E47: =D47 -> 709.4 | F47: =E47 -> 709.4 | G47: =F47 -> 709.4 | H47: =G47 -> 709.4 | I47: =H47 -> 709.4
B48: Total liabilities | C48: $M | D48: =SUM(D43:D47) -> 5999.6 | E48: =SUM(E43:E47) -> 6054.908 | F48: =SUM(F43:F47) -> 6058.0213 | G48: =SUM(G43:G47) -> 6041.1522 | H48: =SUM(H43:H47) -> 6053.4317 | I48: =SUM(I43:I47) -> 6079.7444
B49: Stockholders' equity | C49: $M | D49: =Historicals!$E$83 -> 692.1 | E49: =D49+E26+E56-E61-E62 -> 623.65243 | F49: =E49+F26+F56-F61-F62 -> 680.45477 | G49: =F49+G26+G56-G61-G62 -> 739.94797 | H49: =G49+H26+H56-H61-H62 -> 786.40668 | I49: =H49+I26+I56-I61-I62 -> 831.08879
B50: Check: assets less liabilities and equity | C50: $M | D50: =D42-D48-D49 -> 0 | E50: =ROUND(E42-E48-E49,3) -> 0 | F50: =ROUND(F42-F48-F49,3) -> 0 | G50: =ROUND(G42-G48-G49,3) -> 0 | H50: =ROUND(H42-H48-H49,3) -> 0 | I50: =ROUND(I42-I48-I49,3) -> 0 | J50: Should be zero.
B52: Cash Flow Statement
B53: Line | C53: Units | D53: FY2026A | E53: FY2027E | F53: FY2028E | G53: FY2029E | H53: FY2030E | I53: FY2031E | J53: Note
B54: Net income | C54: $M | E54: =E26 -> 1541.7364 | F54: =F26 -> 1418.1906 | G54: =G26 -> 1320.9282 | H54: =H26 -> 1299.9872 | I54: =I26 -> 1325.7976
B55: Depreciation, amortization and cloud computing amortization | C55: $M | E55: =E12*Inputs!$C$34 -> 224.01878 | F55: =F12*Inputs!$C$34 -> 222.45158 | G55: =G12*Inputs!$C$34 -> 217.75702 | H55: =H12*Inputs!$C$34 -> 219.69643 | I55: =I12*Inputs!$C$34 -> 223.85219
B56: Stock-based compensation | C56: $M | E56: =E12*Inputs!$C$41 -> 108.6906 | F56: =F12*Inputs!$C$41 -> 107.93021 | G56: =G12*Inputs!$C$41 -> 105.65248 | H56: =H12*Inputs!$C$41 -> 106.59345 | I56: =I12*Inputs!$C$41 -> 108.60977
B57: Change in working capital | C57: $M | E57: =-(E35-D35)-(E36-D36)+(E43-D43)+(E44-D44) -> 9.8571264 | F57: =-(F35-E35)-(F36-E36)+(F43-E43)+(F44-E44) -> -7.3686567 | G57: =-(G35-F35)-(G36-F36)+(G43-F43)+(G44-F44) -> -11.102749 | H57: =-(H35-G35)-(H36-G36)+(H43-G43)+(H44-G44) -> 2.3627118 | I57: =-(I35-H35)-(I36-H36)+(I43-H43)+(I44-H44) -> 5.0628233
B58: Cash from operations | C58: $M | D58: =Historicals!$E$88 -> 1978.5 | E58: =E54+E55+E56+E57 -> 1884.3029 | F58: =F54+F55+F56+F57 -> 1741.2038 | G58: =G54+G55+G56+G57 -> 1633.235 | H58: =H54+H55+H56+H57 -> 1628.6398 | I58: =I54+I55+I56+I57 -> 1663.3224
B59: Capex and cloud computing | C59: $M | E59: =Inputs!$C$35 -> 300 | F59: =F12*Inputs!$C$36 -> 271.88526 | G59: =G12*Inputs!$C$36 -> 266.14747 | H59: =H12*Inputs!$C$36 -> 268.51786 | I59: =I12*Inputs!$C$36 -> 273.59712
B60: Free cash flow | C60: $M | E60: =E58-E59 -> 1584.3029 | F60: =F58-F59 -> 1469.3185 | G60: =G58-G59 -> 1367.0875 | H60: =H58-H59 -> 1360.122 | I60: =I58-I59 -> 1389.7253
B61: Dividends | C61: $M | D61: =-Historicals!$E$93 -> 326.1 | E61: =E68*D70 -> 368.8746 | F61: =F68*E70 -> 381.07162 | G61: =G68*F70 -> 399.12969 | H61: =H68*G70 -> 421.1328 | I61: =I68*H70 -> 445.88911
B62: Share repurchases | C62: $M | D62: =-Historicals!$E$94 -> 1554.6 | E62: =Inputs!$C$44 -> 1350 | F62: =MAX(0,F60-F61) -> 1088.2469 | G62: =MAX(0,G60-G61) -> 967.95781 | H62: =MAX(0,H60-H61) -> 938.98916 | I62: =MAX(0,I60-I61) -> 943.83615
B63: Change in cash | C63: $M | E63: =E60-E61-E62 -> -134.57166 | F63: =F60-F61-F62 -> 0 | G63: =G60-G61-G62 -> 0 | H63: =H60-H61-H62 -> 0 | I63: =I60-I61-I62 -> 0
B64: Ending cash | C64: $M | E64: =D33+E63 -> 840.12834 | F64: =E33+F63 -> 840.12834 | G64: =F33+G63 -> 840.12834 | H64: =G33+H63 -> 840.12834 | I64: =H33+I63 -> 840.12834
B66: Shares and Dividends
B67: Line | C67: Units | D67: FY2026A | E67: FY2027E | F67: FY2028E | G67: FY2029E | H67: FY2030E | I67: FY2031E | J67: Note
B68: Dividend per share | C68: $ | D68: 1.6 | E68: =Inputs!$C$42 -> 1.85 | F68: =E68*(1+Inputs!$C$43) -> 1.998 | G68: =F68*(1+Inputs!$C$43) -> 2.15784 | H68: =G68*(1+Inputs!$C$43) -> 2.3304672 | I68: =H68*(1+Inputs!$C$43) -> 2.5169046
B69: Average buyback price | C69: $ | E69: =Inputs!$C$53 -> 115.82 | F69: =E69*(1+Inputs!$C$46) -> 126.2438 | G69: =F69*(1+Inputs!$C$46) -> 137.60574 | H69: =G69*(1+Inputs!$C$46) -> 149.99026 | I69: =H69*(1+Inputs!$C$46) -> 163.48938
B70: Basic shares, end of year | C70: M | D70: =Historicals!$C$105 -> 199.39168 | E70: =D70*(1+Inputs!$C$47)-E62/E69 -> 190.72654 | F70: =E70*(1+Inputs!$C$47)-F62/F69 -> 184.96723 | G70: =F70*(1+Inputs!$C$47)-G62/G69 -> 180.70746 | H70: =G70*(1+Inputs!$C$47)-H62/H69 -> 177.15773 | I70: =H70*(1+Inputs!$C$47)-I62/I69 -> 174.04203 | J70: FY2026A column uses the July 31, 2026 count.
B72: Discounted Cash Flow
B73: Unlevered free cash flow. Stock comp is treated as a real cost. Leases stay inside operating costs.
B74: Line | C74: Units | D74: FY2026A | E74: FY2027E | F74: FY2028E | G74: FY2029E | H74: FY2030E | I74: FY2031E | J74: Note
B75: Operating income | C75: $M | E75: =E19 -> 1949.7931 | F75: =F19 -> 1812.5684 | G75: =G19 -> 1693.6657 | H75: =H19 -> 1668.0655 | I75: =I19 -> 1699.6185
B76: Taxes on operating income | C76: $M | E76: =-E19*Inputs!$C$33 -> -354.86235 | F76: =-F19*Inputs!$C$33 -> -329.88745 | G76: =-G19*Inputs!$C$33 -> -308.24716 | H76: =-H19*Inputs!$C$33 -> -303.58791 | I76: =-I19*Inputs!$C$33 -> -309.33057
B77: D&A | C77: $M | E77: =E55 -> 224.01878 | F77: =F55 -> 222.45158 | G77: =G55 -> 217.75702 | H77: =H55 -> 219.69643 | I77: =I55 -> 223.85219
B78: Capex and cloud computing | C78: $M | E78: =-E59 -> -300 | F78: =-F59 -> -271.88526 | G78: =-G59 -> -266.14747 | H78: =-H59 -> -268.51786 | I78: =-I59 -> -273.59712
B79: Change in working capital | C79: $M | E79: =E57 -> 9.8571264 | F79: =F57 -> -7.3686567 | G79: =G57 -> -11.102749 | H79: =H57 -> 2.3627118 | I79: =I57 -> 5.0628233
B80: Unlevered free cash flow | C80: $M | E80: =SUM(E75:E79) -> 1528.8067 | F80: =SUM(F75:F79) -> 1425.8786 | G80: =SUM(G75:G79) -> 1325.9254 | H80: =SUM(H75:H79) -> 1318.0188 | I80: =SUM(I75:I79) -> 1345.6058
B81: Share of the year still ahead | C81: x | E81: =WACC!$C$28 -> 0.73424658 | F81: =1 -> 1 | G81: =1 -> 1 | H81: =1 -> 1 | I81: =1 -> 1
B82: Cash flow counted | C82: $M | E82: =E80*E81 -> 1122.5211 | F82: =F80*F81 -> 1425.8786 | G82: =G80*G81 -> 1325.9254 | H82: =H80*H81 -> 1318.0188 | I82: =I80*I81 -> 1345.6058
B83: Discount period (mid-year) | C83: years | E83: =WACC!$C$28/2 -> 0.36712329 | F83: =WACC!$C$28+1-0.5 -> 1.2342466 | G83: =WACC!$C$28+2-0.5 -> 2.2342466 | H83: =WACC!$C$28+3-0.5 -> 3.2342466 | I83: =WACC!$C$28+4-0.5 -> 4.2342466
B84: Discount factor | C84: x | E84: =1/(1+WACC!$C$27)^E83 -> 0.9632663 | F84: =1/(1+WACC!$C$27)^F83 -> 0.8817719 | G84: =1/(1+WACC!$C$27)^G83 -> 0.79631207 | H84: =1/(1+WACC!$C$27)^H83 -> 0.71913486 | I84: =1/(1+WACC!$C$27)^I83 -> 0.64943753
B85: Present value | C85: $M | E85: =E82*E84 -> 1081.2867 | F85: =F82*F84 -> 1257.2997 | G85: =G82*G84 -> 1055.8504 | H85: =H82*H84 -> 947.83328 | I85: =I82*I84 -> 873.88692
B87: Value per Share
B88: Item | C88: Units | D88: Value | J88: Note
B89: Present value of FY2027 to FY2031 cash flows | C89: $M | D89: =SUM(E85:I85) -> 5216.157
B90: Terminal value at end of FY2031 | C90: $M | D90: =I80*(1+Inputs!$C$49)/(WACC!$C$27-Inputs!$C$49) -> 17925.279 | J90: Gordon growth.
B91: Present value of terminal value | C91: $M | D91: =D90/(1+WACC!$C$27)^(WACC!$C$28+4) -> 11062.845
B92: Enterprise value | C92: $M | D92: =D89+D91 -> 16279.002
B93: Less: debt | C93: $M | D93: =-Historicals!$E$79 -> -2379 | J93: June 27, 2026.
B94: Plus: cash and short-term investments | C94: $M | D94: =Historicals!$E$64+Historicals!$E$65 -> 1152 | J94: June 27, 2026.
B95: Equity value | C95: $M | D95: =SUM(D92:D94) -> 15052.002
B96: Diluted shares | C96: M | D96: =Inputs!$C$56+Inputs!$C$57 -> 205.59168
B97: Value per share | C97: $ | D97: =D95/D96 -> 73.213088
B98: Upside / (downside) vs today's price | C98: % | D98: =D97/Inputs!$C$53-1 -> -0.3678718
B99: Terminal value as % of enterprise value | C99: % | D99: =D91/D92 -> 0.67957759
B100: Implied exit EV / EBITDA (FY2031) | C100: x | D100: =D90/(I19+I55) -> 9.3192366 | J100: Sanity check on the terminal value.

Sheet Priced In
B2: Tapestry Model: Priced In Case
B3: Income statement, balance sheet, cash flow and DCF. $ in millions except per share. No manual data entry needed.
B5: Income Statement (Adjusted)
B6: FY2026A is pro forma adjusted (excludes Stuart Weitzman and one-time items).
B7: Line | C7: Units | D7: FY2026A | E7: FY2027E | F7: FY2028E | G7: FY2029E | H7: FY2030E | I7: FY2031E | J7: Note
B8: Coach net sales | C8: $M | D8: =Historicals!$E$38 -> 6914.7 | E8: =D8*(1+Inputs!$C$11) -> 7460.9613 | F8: =E8*(1+Inputs!$D$11) -> 8050.3772 | G8: =F8*(1+Inputs!$E$11) -> 8686.357 | H8: =G8*(1+Inputs!$F$11) -> 9372.5793 | I8: =H8*(1+Inputs!$G$11) -> 10113.013
B9: Growth | C9: % | D9: =Historicals!$E$38/Historicals!$D$38-1 -> 0.23509869 | E9: =E8/D8-1 -> 0.079 | F9: =F8/E8-1 -> 0.079 | G9: =G8/F8-1 -> 0.079 | H9: =H8/G8-1 -> 0.079 | I9: =I8/H8-1 -> 0.079
B10: Kate Spade net sales | C10: $M | D10: =Historicals!$E$39 -> 1074.9 | E10: =D10*(1+Inputs!$C$17) -> 988.908 | F10: =E10*(1+Inputs!$D$17) -> 959.24076 | G10: =F10*(1+Inputs!$E$17) -> 959.24076 | H10: =G10*(1+Inputs!$F$17) -> 968.83317 | I10: =H10*(1+Inputs!$G$17) -> 988.20983
B11: Growth | C11: % | D11: =Historicals!$E$39/Historicals!$D$39-1 -> -0.10208003 | E11: =E10/D10-1 -> -0.08 | F11: =F10/E10-1 -> -0.03 | G11: =G10/F10-1 -> 0 | H11: =H10/G10-1 -> 0.01 | I11: =I10/H10-1 -> 0.02
B12: Net sales | C12: $M | D12: =D8+D10 -> 7989.6 | E12: =E8+E10 -> 8449.8693 | F12: =F8+F10 -> 9009.618 | G12: =G8+G10 -> 9645.5978 | H12: =H8+H10 -> 10341.412 | I12: =I8+I10 -> 11101.223
B13: Growth | C13: % | E13: =E12/D12-1 -> 0.057608554 | F13: =F12/E12-1 -> 0.066243475 | G13: =G12/F12-1 -> 0.070588986 | H13: =H12/G12-1 -> 0.07213805 | I13: =I12/H12-1 -> 0.073472597
B14: Cost of sales | C14: $M | D14: =D12-D15 -> 1866.5 | E14: =E12-E15 -> 1960.3697 | F14: =F12-F15 -> 2072.2121 | G14: =G12-G15 -> 2208.8419 | H14: =H12-H15 -> 2357.842 | I14: =I12-I15 -> 2531.0788
B15: Gross profit | C15: $M | D15: =Historicals!$E$27 -> 6123.1 | E15: =E12*Inputs!$C$23 -> 6489.4996 | F15: =F12*Inputs!$D$23 -> 6937.4059 | G15: =G12*Inputs!$E$23 -> 7436.7559 | H15: =H12*Inputs!$F$23 -> 7983.5704 | I15: =I12*Inputs!$G$23 -> 8570.144
B16: Gross margin | C16: % | D16: =D15/D12 -> 0.7663838 | E16: =E15/E12 -> 0.768 | F16: =F15/F12 -> 0.77 | G16: =G15/G12 -> 0.771 | H16: =H15/H12 -> 0.772 | I16: =I15/I12 -> 0.772
B17: SG&A | C17: $M | D17: =Historicals!$E$28 -> 4257.3 | E17: =E15-E19 -> 4474.2058 | F17: =F15-F19 -> 4757.0783 | G17: =G15-G19 -> 5083.23 | H17: =H15-H19 -> 5449.9243 | I17: =I15-I19 -> 5850.3444
B18: % of sales | C18: % | D18: =D17/D12 -> 0.53285521 | E18: =E17/E12 -> 0.5295 | F18: =F17/F12 -> 0.528 | G18: =G17/G12 -> 0.527 | H18: =H17/H12 -> 0.527 | I18: =I17/I12 -> 0.527
B19: Operating income | C19: $M | D19: =Historicals!$E$29 -> 1865.8 | E19: =E12*Inputs!$C$29 -> 2015.2938 | F19: =F12*Inputs!$D$29 -> 2180.3276 | G19: =G12*Inputs!$E$29 -> 2353.5259 | H19: =H12*Inputs!$F$29 -> 2533.646 | I19: =I12*Inputs!$G$29 -> 2719.7996
B20: Operating margin | C20: % | D20: =D19/D12 -> 0.23352859 | E20: =E19/E12 -> 0.2385 | F20: =F19/F12 -> 0.242 | G20: =G19/G12 -> 0.244 | H20: =H19/H12 -> 0.245 | I20: =I19/I12 -> 0.245
B21: Interest expense on senior notes | C21: $M | E21: =Historicals!$D$98*Historicals!$C$98+Historicals!$D$99*Historicals!$C$99+Historicals!$D$100*Historicals!$C$100+Historicals!$D$101*Historicals!$C$101 -> 111.10975 | F21: =Historicals!$D$98*WACC!$C$11+Historicals!$D$99*Historicals!$C$99+Historicals!$D$100*Historicals!$C$100+Historicals!$D$101*Historicals!$C$101 -> 119.53616 | G21: =Historicals!$D$98*WACC!$C$11+Historicals!$D$99*Historicals!$C$99+Historicals!$D$100*Historicals!$C$100+Historicals!$D$101*Historicals!$C$101 -> 119.53616 | H21: =Historicals!$D$98*WACC!$C$11+Historicals!$D$99*Historicals!$C$99+Historicals!$D$100*Historicals!$C$100+Historicals!$D$101*Historicals!$C$101 -> 119.53616 | I21: =Historicals!$D$98*WACC!$C$11+Historicals!$D$99*Historicals!$C$99+Historicals!$D$100*Historicals!$C$100+Historicals!$D$101*Historicals!$C$101 -> 119.53616 | J21: The 2027 notes are refinanced at today's cost of debt from FY2028.
B22: Interest earned on cash | C22: $M | E22: =(D33+D34)*Inputs!$C$48 -> 46.08 | F22: =(E33+E34)*Inputs!$C$48 -> 43.42718 | G22: =(F33+F34)*Inputs!$C$48 -> 43.42718 | H22: =(G33+G34)*Inputs!$C$48 -> 43.42718 | I22: =(H33+H34)*Inputs!$C$48 -> 43.42718 | J22: On cash at the start of the year.
B23: Net interest expense (other income for FY2026A) | C23: $M | D23: =Historicals!$E$30+Historicals!$E$31 -> 53.8 | E23: =E21-E22 -> 65.02975 | F23: =F21-F22 -> 76.108982 | G23: =G21-G22 -> 76.108982 | H23: =H21-H22 -> 76.108982 | I23: =I21-I22 -> 76.108982
B24: Income before taxes | C24: $M | D24: =D19-D23 -> 1812 | E24: =E19-E23 -> 1950.2641 | F24: =F19-F23 -> 2104.2186 | G24: =G19-G23 -> 2277.4169 | H24: =H19-H23 -> 2457.5371 | I24: =I19-I23 -> 2643.6906
B25: Income taxes | C25: $M | D25: =Historicals!$E$32 -> 330 | E25: =E24*Inputs!$C$33 -> 354.94806 | F25: =F24*Inputs!$C$33 -> 382.96778 | G25: =G24*Inputs!$C$33 -> 414.48987 | H25: =H24*Inputs!$C$33 -> 447.27175 | I25: =I24*Inputs!$C$33 -> 481.15169
B26: Adjusted net income | C26: $M | D26: =D24-D25 -> 1482 | E26: =E24-E25 -> 1595.316 | F26: =F24-F25 -> 1721.2508 | G26: =G24-G25 -> 1862.927 | H26: =H24-H25 -> 2010.2653 | I26: =I24-I25 -> 2162.5389
B27: Diluted shares (average) | C27: M | D27: =Historicals!$E$20 -> 210.2 | E27: =(D70+E70)/2+Inputs!$C$57 -> 201.25911 | F27: =(E70+F70)/2+Inputs!$C$57 -> 192.70972 | G27: =(F70+G70)/2+Inputs!$C$57 -> 184.18635 | H27: =(G70+H70)/2+Inputs!$C$57 -> 175.49995 | I27: =(H70+I70)/2+Inputs!$C$57 -> 166.6901
B28: Adjusted diluted EPS | C28: $ | D28: =D26/D27 -> 7.0504282 | E28: =E26/E27 -> 7.9266774 | F28: =F26/F27 -> 8.9318319 | G28: =G26/G27 -> 10.11436 | H28: =H26/H27 -> 11.454507 | I28: =I26/I27 -> 12.973409
B29: Growth | C29: % | E29: =E28/D28-1 -> 0.12428313 | F29: =F28/E28-1 -> 0.12680654 | G29: =G28/F28-1 -> 0.13239475 | H29: =H28/G28-1 -> 0.13249946 | I29: =I28/H28-1 -> 0.13260307
B31: Balance Sheet
B32: Line | C32: Units | D32: FY2026A | E32: FY2027E | F32: FY2028E | G32: FY2029E | H32: FY2030E | I32: FY2031E | J32: Note
B33: Cash and cash equivalents | C33: $M | D33: =Historicals!$E$64 -> 974.7 | E33: =E64 -> 908.37951 | F33: =F64 -> 908.37951 | G33: =G64 -> 908.37951 | H33: =H64 -> 908.37951 | I33: =I64 -> 908.37951
B34: Short-term investments | C34: $M | D34: =Historicals!$E$65 -> 177.3 | E34: =D34 -> 177.3 | F34: =E34 -> 177.3 | G34: =F34 -> 177.3 | H34: =G34 -> 177.3 | I34: =H34 -> 177.3
B35: Trade accounts receivable | C35: $M | D35: =Historicals!$E$66 -> 237.1 | E35: =E12*Inputs!$C$37/365 -> 250.02353 | F35: =F12*Inputs!$C$37/365 -> 266.58596 | G35: =G12*Inputs!$C$37/365 -> 285.40399 | H35: =H12*Inputs!$C$37/365 -> 305.99248 | I35: =I12*Inputs!$C$37/365 -> 328.47454
B36: Inventories | C36: $M | D36: =Historicals!$E$67 -> 826.2 | E36: =E14*Inputs!$C$38/365 -> 867.93353 | F36: =F14*Inputs!$C$38/365 -> 917.45064 | G36: =G14*Inputs!$C$38/365 -> 977.94206 | H36: =H14*Inputs!$C$38/365 -> 1043.9103 | I36: =I14*Inputs!$C$38/365 -> 1120.6091
B37: Other current assets | C37: $M | D37: =Historicals!$E$68 -> 667 | E37: =D37 -> 667 | F37: =E37 -> 667 | G37: =F37 -> 667 | H37: =G37 -> 667 | I37: =H37 -> 667
B38: Property, equipment and cloud computing assets | C38: $M | D38: =Historicals!$E$69 -> 502.1 | E38: =D38+E59-E55 -> 573.95353 | F38: =E38+F59-F55 -> 628.01124 | G38: =F38+G59-G55 -> 685.88482 | H38: =G38+H59-H55 -> 747.9333 | I38: =H38+I59-I55 -> 814.54064
B39: Operating lease right-of-use assets | C39: $M | D39: =Historicals!$E$70 -> 1417.2 | E39: =D39 -> 1417.2 | F39: =E39 -> 1417.2 | G39: =F39 -> 1417.2 | H39: =G39 -> 1417.2 | I39: =H39 -> 1417.2
B40: Goodwill and intangibles | C40: $M | D40: =Historicals!$E$71+Historicals!$E$72 -> 1674.2 | E40: =D40 -> 1674.2 | F40: =E40 -> 1674.2 | G40: =F40 -> 1674.2 | H40: =G40 -> 1674.2 | I40: =H40 -> 1674.2
B41: Other assets | C41: $M | D41: =Historicals!$E$73 -> 215.9 | E41: =D41 -> 215.9 | F41: =E41 -> 215.9 | G41: =F41 -> 215.9 | H41: =G41 -> 215.9 | I41: =H41 -> 215.9
B42: Total assets | C42: $M | D42: =SUM(D33:D41) -> 6691.7 | E42: =SUM(E33:E41) -> 6751.8901 | F42: =SUM(F33:F41) -> 6872.0273 | G42: =SUM(G33:G41) -> 7009.2104 | H42: =SUM(H33:H41) -> 7157.8156 | I42: =SUM(I33:I41) -> 7323.6038
B43: Accounts payable | C43: $M | D43: =Historicals!$E$75 -> 582.3 | E43: =E14*Inputs!$C$39/365 -> 611.74276 | F43: =F14*Inputs!$C$39/365 -> 646.64373 | G43: =G14*Inputs!$C$39/365 -> 689.2797 | H43: =H14*Inputs!$C$39/365 -> 735.77591 | I43: =I14*Inputs!$C$39/365 -> 789.83528
B44: Accrued liabilities | C44: $M | D44: =Historicals!$E$76 -> 754.9 | E44: =E12*Inputs!$C$40 -> 798.51265 | F44: =F12*Inputs!$C$40 -> 851.4089 | G44: =G12*Inputs!$C$40 -> 911.50899 | H44: =H12*Inputs!$C$40 -> 977.26347 | I44: =I12*Inputs!$C$40 -> 1049.0656
B45: Operating lease liabilities | C45: $M | D45: =Historicals!$E$77+Historicals!$E$80 -> 1574 | E45: =D45 -> 1574 | F45: =E45 -> 1574 | G45: =F45 -> 1574 | H45: =G45 -> 1574 | I45: =H45 -> 1574
B46: Debt | C46: $M | D46: =Historicals!$E$79+Historicals!$E$78 -> 2379 | E46: =D46 -> 2379 | F46: =E46 -> 2379 | G46: =F46 -> 2379 | H46: =G46 -> 2379 | I46: =H46 -> 2379 | J46: Notes are refinanced when they mature.
B47: Other liabilities | C47: $M | D47: =Historicals!$E$81 -> 709.4 | E47: =D47 -> 709.4 | F47: =E47 -> 709.4 | G47: =F47 -> 709.4 | H47: =G47 -> 709.4 | I47: =H47 -> 709.4
B48: Total liabilities | C48: $M | D48: =SUM(D43:D47) -> 5999.6 | E48: =SUM(E43:E47) -> 6072.6554 | F48: =SUM(F43:F47) -> 6160.4526 | G48: =SUM(G43:G47) -> 6263.1887 | H48: =SUM(H43:H47) -> 6375.4394 | I48: =SUM(I43:I47) -> 6501.3008
B49: Stockholders' equity | C49: $M | D49: =Historicals!$E$83 -> 692.1 | E49: =D49+E26+E56-E61-E62 -> 679.2347 | F49: =E49+F26+F56-F61-F62 -> 711.57471 | G49: =F49+G26+G56-G61-G62 -> 746.02169 | H49: =G49+H26+H56-H61-H62 -> 782.37624 | I49: =H49+I26+I56-I61-I62 -> 822.30299
B50: Check: assets less liabilities and equity | C50: $M | D50: =D42-D48-D49 -> 0 | E50: =ROUND(E42-E48-E49,3) -> 0 | F50: =ROUND(F42-F48-F49,3) -> 0 | G50: =ROUND(G42-G48-G49,3) -> 0 | H50: =ROUND(H42-H48-H49,3) -> 0 | I50: =ROUND(I42-I48-I49,3) -> 0 | J50: Should be zero.
B52: Cash Flow Statement
B53: Line | C53: Units | D53: FY2026A | E53: FY2027E | F53: FY2028E | G53: FY2029E | H53: FY2030E | I53: FY2031E | J53: Note
B54: Net income | C54: $M | E54: =E26 -> 1595.316 | F54: =F26 -> 1721.2508 | G54: =G26 -> 1862.927 | H54: =H26 -> 2010.2653 | I54: =I26 -> 2162.5389
B55: Depreciation, amortization and cloud computing amortization | C55: $M | E55: =E12*Inputs!$C$34 -> 228.14647 | F55: =F12*Inputs!$C$34 -> 243.25969 | G55: =G12*Inputs!$C$34 -> 260.43114 | H55: =H12*Inputs!$C$34 -> 279.21814 | I55: =I12*Inputs!$C$34 -> 299.73302
B56: Stock-based compensation | C56: $M | E56: =E12*Inputs!$C$41 -> 110.69329 | F56: =F12*Inputs!$C$41 -> 118.026 | G56: =G12*Inputs!$C$41 -> 126.35733 | H56: =H12*Inputs!$C$41 -> 135.4725 | I56: =I12*Inputs!$C$41 -> 145.42602
B57: Change in working capital | C57: $M | E57: =-(E35-D35)-(E36-D36)+(E43-D43)+(E44-D44) -> 18.398342 | F57: =-(F35-E35)-(F36-E36)+(F43-E43)+(F44-E44) -> 21.7177 | G57: =-(G35-F35)-(G36-F36)+(G43-F43)+(G44-F44) -> 23.426608 | H57: =-(H35-G35)-(H36-G36)+(H43-G43)+(H44-G44) -> 25.693921 | I57: =-(I35-H35)-(I36-H36)+(I43-H43)+(I44-H44) -> 26.680587
B58: Cash from operations | C58: $M | D58: =Historicals!$E$88 -> 1978.5 | E58: =E54+E55+E56+E57 -> 1952.5541 | F58: =F54+F55+F56+F57 -> 2104.2542 | G58: =G54+G55+G56+G57 -> 2273.1421 | H58: =H54+H55+H56+H57 -> 2450.6499 | I58: =I54+I55+I56+I57 -> 2634.3785
B59: Capex and cloud computing | C59: $M | E59: =Inputs!$C$35 -> 300 | F59: =F12*Inputs!$C$36 -> 297.31739 | G59: =G12*Inputs!$C$36 -> 318.30473 | H59: =H12*Inputs!$C$36 -> 341.26661 | I59: =I12*Inputs!$C$36 -> 366.34035
B60: Free cash flow | C60: $M | E60: =E58-E59 -> 1652.5541 | F60: =F58-F59 -> 1806.9368 | G60: =G58-G59 -> 1954.8374 | H60: =H58-H59 -> 2109.3833 | I60: =I58-I59 -> 2268.0382
B61: Dividends | C61: $M | D61: =-Historicals!$E$93 -> 326.1 | E61: =E68*D70 -> 368.8746 | F61: =F68*E70 -> 381.07162 | G61: =G68*F70 -> 393.35891 | H61: =H68*G70 -> 404.7551 | I61: =I68*H70 -> 415.08811
B62: Share repurchases | C62: $M | D62: =-Historicals!$E$94 -> 1554.6 | E62: =Inputs!$C$44 -> 1350 | F62: =MAX(0,F60-F61) -> 1425.8652 | G62: =MAX(0,G60-G61) -> 1561.4785 | H62: =MAX(0,H60-H61) -> 1704.6282 | I62: =MAX(0,I60-I61) -> 1852.9501
B63: Change in cash | C63: $M | E63: =E60-E61-E62 -> -66.320488 | F63: =F60-F61-F62 -> 0 | G63: =G60-G61-G62 -> 0 | H63: =H60-H61-H62 -> 0 | I63: =I60-I61-I62 -> 0
B64: Ending cash | C64: $M | E64: =D33+E63 -> 908.37951 | F64: =E33+F63 -> 908.37951 | G64: =F33+G63 -> 908.37951 | H64: =G33+H63 -> 908.37951 | I64: =H33+I63 -> 908.37951
B66: Shares and Dividends
B67: Line | C67: Units | D67: FY2026A | E67: FY2027E | F67: FY2028E | G67: FY2029E | H67: FY2030E | I67: FY2031E | J67: Note
B68: Dividend per share | C68: $ | D68: 1.6 | E68: =Inputs!$C$42 -> 1.85 | F68: =E68*(1+Inputs!$C$43) -> 1.998 | G68: =F68*(1+Inputs!$C$43) -> 2.15784 | H68: =G68*(1+Inputs!$C$43) -> 2.3304672 | I68: =H68*(1+Inputs!$C$43) -> 2.5169046
B69: Average buyback price | C69: $ | E69: =Inputs!$C$53 -> 115.82 | F69: =E69*(1+Inputs!$C$46) -> 126.2438 | G69: =F69*(1+Inputs!$C$46) -> 137.60574 | H69: =G69*(1+Inputs!$C$46) -> 149.99026 | I69: =H69*(1+Inputs!$C$46) -> 163.48938
B70: Basic shares, end of year | C70: M | D70: =Historicals!$C$105 -> 199.39168 | E70: =D70*(1+Inputs!$C$47)-E62/E69 -> 190.72654 | F70: =E70*(1+Inputs!$C$47)-F62/F69 -> 182.2929 | G70: =F70*(1+Inputs!$C$47)-G62/G69 -> 173.67981 | H70: =G70*(1+Inputs!$C$47)-H62/H69 -> 164.92008 | I70: =H70*(1+Inputs!$C$47)-I62/I69 -> 156.06012 | J70: FY2026A column uses the July 31, 2026 count.
B72: Discounted Cash Flow
B73: Unlevered free cash flow. Stock comp is treated as a real cost. Leases stay inside operating costs.
B74: Line | C74: Units | D74: FY2026A | E74: FY2027E | F74: FY2028E | G74: FY2029E | H74: FY2030E | I74: FY2031E | J74: Note
B75: Operating income | C75: $M | E75: =E19 -> 2015.2938 | F75: =F19 -> 2180.3276 | G75: =G19 -> 2353.5259 | H75: =H19 -> 2533.646 | I75: =I19 -> 2719.7996
B76: Taxes on operating income | C76: $M | E76: =-E19*Inputs!$C$33 -> -366.78348 | F76: =-F19*Inputs!$C$33 -> -396.81962 | G76: =-G19*Inputs!$C$33 -> -428.34171 | H76: =-H19*Inputs!$C$33 -> -461.12358 | I76: =-I19*Inputs!$C$33 -> -495.00353
B77: D&A | C77: $M | E77: =E55 -> 228.14647 | F77: =F55 -> 243.25969 | G77: =G55 -> 260.43114 | H77: =H55 -> 279.21814 | I77: =I55 -> 299.73302
B78: Capex and cloud computing | C78: $M | E78: =-E59 -> -300 | F78: =-F59 -> -297.31739 | G78: =-G59 -> -318.30473 | H78: =-H59 -> -341.26661 | I78: =-I59 -> -366.34035
B79: Change in working capital | C79: $M | E79: =E57 -> 18.398342 | F79: =F57 -> 21.7177 | G79: =G57 -> 23.426608 | H79: =H57 -> 25.693921 | I79: =I57 -> 26.680587
B80: Unlevered free cash flow | C80: $M | E80: =SUM(E75:E79) -> 1595.0552 | F80: =SUM(F75:F79) -> 1751.1679 | G80: =SUM(G75:G79) -> 1890.7372 | H80: =SUM(H75:H79) -> 2036.1679 | I80: =SUM(I75:I79) -> 2184.8693
B81: Share of the year still ahead | C81: x | E81: =WACC!$C$28 -> 0.73424658 | F81: =1 -> 1 | G81: =1 -> 1 | H81: =1 -> 1 | I81: =1 -> 1
B82: Cash flow counted | C82: $M | E82: =E80*E81 -> 1171.1638 | F82: =F80*F81 -> 1751.1679 | G82: =G80*G81 -> 1890.7372 | H82: =H80*H81 -> 2036.1679 | I82: =I80*I81 -> 2184.8693
B83: Discount period (mid-year) | C83: years | E83: =WACC!$C$28/2 -> 0.36712329 | F83: =WACC!$C$28+1-0.5 -> 1.2342466 | G83: =WACC!$C$28+2-0.5 -> 2.2342466 | H83: =WACC!$C$28+3-0.5 -> 3.2342466 | I83: =WACC!$C$28+4-0.5 -> 4.2342466
B84: Discount factor | C84: x | E84: =1/(1+WACC!$C$27)^E83 -> 0.9632663 | F84: =1/(1+WACC!$C$27)^F83 -> 0.8817719 | G84: =1/(1+WACC!$C$27)^G83 -> 0.79631207 | H84: =1/(1+WACC!$C$27)^H83 -> 0.71913486 | I84: =1/(1+WACC!$C$27)^I83 -> 0.64943753
B85: Present value | C85: $M | E85: =E82*E84 -> 1128.1426 | F85: =F82*F84 -> 1544.1307 | G85: =G82*G84 -> 1505.6168 | H85: =H82*H84 -> 1464.2793 | I85: =I82*I84 -> 1418.9361
B87: Value per Share
B88: Item | C88: Units | D88: Value | J88: Note
B89: Present value of FY2027 to FY2031 cash flows | C89: $M | D89: =SUM(E85:I85) -> 7061.1056
B90: Terminal value at end of FY2031 | C90: $M | D90: =I80*(1+Inputs!$C$49)/(WACC!$C$27-Inputs!$C$49) -> 29105.396 | J90: Gordon growth.
B91: Present value of terminal value | C91: $M | D91: =D90/(1+WACC!$C$27)^(WACC!$C$28+4) -> 17962.816
B92: Enterprise value | C92: $M | D92: =D89+D91 -> 25023.922
B93: Less: debt | C93: $M | D93: =-Historicals!$E$79 -> -2379 | J93: June 27, 2026.
B94: Plus: cash and short-term investments | C94: $M | D94: =Historicals!$E$64+Historicals!$E$65 -> 1152 | J94: June 27, 2026.
B95: Equity value | C95: $M | D95: =SUM(D92:D94) -> 23796.922
B96: Diluted shares | C96: M | D96: =Inputs!$C$56+Inputs!$C$57 -> 205.59168
B97: Value per share | C97: $ | D97: =D95/D96 -> 115.74847
B98: Upside / (downside) vs today's price | C98: % | D98: =D97/Inputs!$C$53-1 -> -0.00061761816
B99: Terminal value as % of enterprise value | C99: % | D99: =D91/D92 -> 0.71782578
B100: Implied exit EV / EBITDA (FY2031) | C100: x | D100: =D90/(I19+I55) -> 9.6390403 | J100: Sanity check on the terminal value.

Sheet WACC
B2: Cost of Capital
B3: No manual data entry needed.
B5: Cost of Debt
B6: Market yield on Tapestry's 5.500% 2035 notes at June 27, 2026, moved up by the rise in the 10-year Treasury since then.
B7: Item | C7: Value | D7: Units | E7: Note
B8: Price of 5.500% 2035 notes, June 27, 2026 | C8: =Historicals!$E$101/Historicals!$D$101*100 -> 101.02667 | D8: % of par | E8: Fair value / principal from the 10-K debt note.
B9: Yield to maturity, June 27, 2026 | C9: =YIELD(DATE(2026,6,27),DATE(2035,3,11),Historicals!$C$101,C8,100,2,0) -> 0.053496628 | D9: %
B10: Change in 10-year Treasury since then | C10: =Inputs!$C$58-'Market Data'!$C$28 -> 0.009 | D10: %
B11: Pre-tax cost of debt | C11: =C9+C10 -> 0.062496628 | D11: %
B12: After-tax cost of debt | C12: =WACC!$C$11*(1-Inputs!$C$61) -> 0.049372336 | D12: %
B14: Cost of Equity (CAPM)
B15: Item | C15: Value | D15: Units | E15: Note
B16: Risk-free rate | C16: =Inputs!$C$58 -> 0.0528 | D16: %
B17: Beta | C17: =Inputs!$C$59 -> 1.43 | D17: x
B18: Equity risk premium | C18: =Inputs!$C$60 -> 0.0423 | D18: %
B19: Cost of equity | C19: =C16+C17*C18 -> 0.113289 | D19: %
B21: Weights and WACC
B22: Item | C22: Value | D22: Units | E22: Note
B23: Market value of equity | C23: =Inputs!$C$53*Inputs!$C$56 -> 23093.544 | D23: $M
B24: Debt | C24: =Historicals!$E$79 -> 2379 | D24: $M | E24: Book value (the notes trade close to par). Leases are left out on both sides of the DCF.
B25: Equity weight | C25: =C23/(C23+C24) -> 0.90660532 | D25: %
B26: Debt weight | C26: =C24/(C23+C24) -> 0.093394676 | D26: %
B27: WACC | C27: =C25*WACC!$C$19+C26*WACC!$C$12 -> 0.10731952 | D27: %
B28: Stub: valuation date to end of FY2027 | C28: =(Inputs!$C$55-Inputs!$C$54)/365 -> 0.73424658 | D28: years

Sheet Comps
B2: Comparable Companies
B3: Trading multiples from stockanalysis.com, Sep 29 to Oct 8, 2026. Market cap and EV in billions of local currency.
B5: Peer Multiples
B6: European peers report under IFRS 16, which adds rent back into EBITDA, so I compare on P/E and EV/EBIT, not EV/EBITDA.
B7: Company | C7: Price date | D7: Currency | E7: Market cap | F7: EV | G7: Fwd P/E | H7: EV / EBIT | I7: EV / EBITDA | J7: Op. margin | K7: Why it's here
B8: Ralph Lauren | C8: Oct 6, 2026 | D8: USD | E8: 21.97 | F8: 23.03 | G8: 18.79 | H8: 16.97 | I8: 14.45 | J8: 0.1624 | K8: Closest U.S. premium lifestyle brand.
B9: Capri Holdings | C9: Oct 5, 2026 | D9: USD | E9: 1.62 | F9: 2.9 | G9: 7.68 | H9: 38.54 | I9: 14.82 | J9: 0.0218 | K9: Michael Kors, Coach's most direct rival. Distressed.
B10: PVH | C10: Oct 8, 2026 | D10: USD | E10: 3.76 | F10: 6.95 | G10: 7.34 | H10: 9.98 | I10: 7.41 | J10: 0.0766 | K10: U.S. premium apparel (Calvin Klein, Tommy Hilfiger).
B11: Levi Strauss | C11: Oct 7, 2026 | D11: USD | E11: 7.51 | F11: 9.06 | G11: 12.16 | H11: 11.5 | I11: 8.97 | J11: 0.1179 | K11: U.S. heritage brand with a growing direct-to-consumer business.
B12: LVMH | C12: Oct 7, 2026 | D12: EUR | E12: 188.04 | F12: 214.58 | G12: 16.47 | H12: 12.41 | I12: 9.31 | J12: 0.2182 | K12: Global luxury leader (Louis Vuitton).
B13: Kering | C13: Oct 7, 2026 | D13: EUR | E13: 25.73 | F13: 36.04 | G13: 26.64 | H13: 23.57 | I13: 10.19 | J13: 0.1129 | K13: Luxury handbags (Gucci). Earnings depressed.
B14: Prada | C14: Sep 29, 2026 | D14: HKD | E14: 99.54 | F14: 133.86 | G14: 13.75 | H14: 12.35 | I14: 7.36 | J14: 0.2008 | K14: Luxury handbags (Prada, Miu Miu).
B15: Moncler | C15: Sep 29, 2026 | D15: EUR | E15: 12.16 | F15: 12.25 | G15: 18.18 | H15: 13.22 | I15: 10.8 | J15: 0.2899 | K15: Luxury brand with high margins.
B16: Burberry | C16: Oct 7, 2026 | D16: GBP | E16: 3.64 | F16: 4.5 | G16: 26.81 | H16: 28.11 | I16: 9.14 | J16: 0.0661 | K16: British luxury, mid-turnaround.
B17: Median | G17: =MEDIAN(G8:G16) -> 16.47 | H17: =MEDIAN(H8:H16) -> 13.22 | I17: =MEDIAN(I8:I16) -> 9.31
B18: 25th percentile | G18: =QUARTILE(G8:G16,1) -> 12.16 | H18: =QUARTILE(H8:H16,1) -> 12.35 | I18: =QUARTILE(I8:I16,1) -> 8.97
B19: 75th percentile | G19: =QUARTILE(G8:G16,3) -> 18.79 | H19: =QUARTILE(H8:H16,3) -> 23.57 | I19: =QUARTILE(I8:I16,3) -> 10.8
B21: Tapestry today | C21: Oct 8, 2026 | D21: USD | E21: =Inputs!$C$53*Inputs!$C$56/1000 -> 23.093544 | F21: =E21+(Historicals!$E$79+Historicals!$E$77+Historicals!$E$80-Historicals!$E$64-Historicals!$E$65)/1000 -> 25.894544 | G21: =Inputs!$C$53/AVERAGE('Market Data'!$C$18,'Market Data'!$D$18) -> 14.75414 | H21: =F21*1000/Historicals!$E$29 -> 13.878521 | I21: =F21*1000/(Historicals!$E$29+Historicals!$E$90+Historicals!$E$91) -> 12.43137 | J21: =Historicals!$E$29/Historicals!$E$26 -> 0.23352859 | K21: Same basis as the peers: EV includes lease liabilities. Fwd P/E on FY2027 guidance midpoint; EV/EBIT on FY2026 adjusted.
B23: What the Peer Multiples Imply for Tapestry
B24: Method | C24: Multiple | D24: Tapestry metric | E24: Value / share | K24: Note
B25: Fwd P/E: 25th percentile | C25: =G18 -> 12.16 | D25: =AVERAGE('Market Data'!$C$18,'Market Data'!$D$18) -> 7.85 | E25: =C25*D25 -> 95.456 | K25: FY2027 EPS guidance midpoint.
B26: Fwd P/E: median | C26: =G17 -> 16.47 | D26: =AVERAGE('Market Data'!$C$18,'Market Data'!$D$18) -> 7.85 | E26: =C26*D26 -> 129.2895 | K26: FY2027 EPS guidance midpoint.
B27: Fwd P/E: 75th percentile | C27: =G19 -> 18.79 | D27: =AVERAGE('Market Data'!$C$18,'Market Data'!$D$18) -> 7.85 | E27: =C27*D27 -> 147.5015 | K27: FY2027 EPS guidance midpoint.
B28: EV/EBIT: 25th percentile | C28: =H18 -> 12.35 | D28: =Historicals!$E$29 -> 1865.8 | E28: =(C28*D28-(Historicals!$E$79+Historicals!$E$77+Historicals!$E$80-Historicals!$E$64-Historicals!$E$65))/(Inputs!$C$56+Inputs!$C$57) -> 98.455493 | K28: FY2026 adjusted operating income, less debt and leases, plus cash.
B29: EV/EBIT: median | C29: =H17 -> 13.22 | D29: =Historicals!$E$29 -> 1865.8 | E29: =(C29*D29-(Historicals!$E$79+Historicals!$E$77+Historicals!$E$80-Historicals!$E$64-Historicals!$E$65))/(Inputs!$C$56+Inputs!$C$57) -> 106.35098 | K29: FY2026 adjusted operating income, less debt and leases, plus cash.
B30: EV/EBIT: 75th percentile | C30: =H19 -> 23.57 | D30: =Historicals!$E$29 -> 1865.8 | E30: =(C30*D30-(Historicals!$E$79+Historicals!$E$77+Historicals!$E$80-Historicals!$E$64-Historicals!$E$65))/(Inputs!$C$56+Inputs!$C$57) -> 200.28002 | K30: FY2026 adjusted operating income, less debt and leases, plus cash.

Sheet Sensitivity
B2: Sensitivity: Base Case Value per Share
B3: WACC across, terminal growth down. No manual data entry needed.
B5: Value per Share ($)
B6: The center column is the model's WACC. Each column is 0.5 points apart.
B7: Terminal growth / WACC | C7: -1.0% | D7: -0.5% | E7: Model | F7: +0.5% | G7: +1.0%
B8: WACC used | C8: =WACC!$C$27+(-0.01) -> 0.097319524 | D8: =WACC!$C$27+(-0.005) -> 0.10231952 | E8: =WACC!$C$27+(0) -> 0.10731952 | F8: =WACC!$C$27+(0.005) -> 0.11231952 | G8: =WACC!$C$27+(0.01) -> 0.11731952
B9: 0.02 | C9: =(SUMPRODUCT(Base!$E$82:$I$82,1/(1+C$8)^Base!$E$83:$I$83)+Base!$I$80*(1+$B9)/(C$8-$B9)/(1+C$8)^(WACC!$C$28+4)-Historicals!$E$79+Historicals!$E$64+Historicals!$E$65)/Base!$D$96 -> 107.917 | D9: =(SUMPRODUCT(Base!$E$82:$I$82,1/(1+D$8)^Base!$E$83:$I$83)+Base!$I$80*(1+$B9)/(D$8-$B9)/(1+D$8)^(WACC!$C$28+4)-Historicals!$E$79+Historicals!$E$64+Historicals!$E$65)/Base!$D$96 -> 101.061 | E9: =(SUMPRODUCT(Base!$E$82:$I$82,1/(1+E$8)^Base!$E$83:$I$83)+Base!$I$80*(1+$B9)/(E$8-$B9)/(1+E$8)^(WACC!$C$28+4)-Historicals!$E$79+Historicals!$E$64+Historicals!$E$65)/Base!$D$96 -> 94.996128 | F9: =(SUMPRODUCT(Base!$E$82:$I$82,1/(1+F$8)^Base!$E$83:$I$83)+Base!$I$80*(1+$B9)/(F$8-$B9)/(1+F$8)^(WACC!$C$28+4)-Historicals!$E$79+Historicals!$E$64+Historicals!$E$65)/Base!$D$96 -> 89.593592 | G9: =(SUMPRODUCT(Base!$E$82:$I$82,1/(1+G$8)^Base!$E$83:$I$83)+Base!$I$80*(1+$B9)/(G$8-$B9)/(1+G$8)^(WACC!$C$28+4)-Historicals!$E$79+Historicals!$E$64+Historicals!$E$65)/Base!$D$96 -> 84.751088
B10: 0.025 | C10: =(SUMPRODUCT(Base!$E$82:$I$82,1/(1+C$8)^Base!$E$83:$I$83)+Base!$I$80*(1+$B10)/(C$8-$B10)/(1+C$8)^(WACC!$C$28+4)-Historicals!$E$79+Historicals!$E$64+Historicals!$E$65)/Base!$D$96 -> 113.91631 | D10: =(SUMPRODUCT(Base!$E$82:$I$82,1/(1+D$8)^Base!$E$83:$I$83)+Base!$I$80*(1+$B10)/(D$8-$B10)/(1+D$8)^(WACC!$C$28+4)-Historicals!$E$79+Historicals!$E$64+Historicals!$E$65)/Base!$D$96 -> 106.24281 | E10: =(SUMPRODUCT(Base!$E$82:$I$82,1/(1+E$8)^Base!$E$83:$I$83)+Base!$I$80*(1+$B10)/(E$8-$B10)/(1+E$8)^(WACC!$C$28+4)-Historicals!$E$79+Historicals!$E$64+Historicals!$E$65)/Base!$D$96 -> 99.507617 | F10: =(SUMPRODUCT(Base!$E$82:$I$82,1/(1+F$8)^Base!$E$83:$I$83)+Base!$I$80*(1+$B10)/(F$8-$B10)/(1+F$8)^(WACC!$C$28+4)-Historicals!$E$79+Historicals!$E$64+Historicals!$E$65)/Base!$D$96 -> 93.549286 | G10: =(SUMPRODUCT(Base!$E$82:$I$82,1/(1+G$8)^Base!$E$83:$I$83)+Base!$I$80*(1+$B10)/(G$8-$B10)/(1+G$8)^(WACC!$C$28+4)-Historicals!$E$79+Historicals!$E$64+Historicals!$E$65)/Base!$D$96 -> 88.24137
B11: 0.03 | C11: =(SUMPRODUCT(Base!$E$82:$I$82,1/(1+C$8)^Base!$E$83:$I$83)+Base!$I$80*(1+$B11)/(C$8-$B11)/(1+C$8)^(WACC!$C$28+4)-Historicals!$E$79+Historicals!$E$64+Historicals!$E$65)/Base!$D$96 -> 120.8068 | D11: =(SUMPRODUCT(Base!$E$82:$I$82,1/(1+D$8)^Base!$E$83:$I$83)+Base!$I$80*(1+$B11)/(D$8-$B11)/(1+D$8)^(WACC!$C$28+4)-Historicals!$E$79+Historicals!$E$64+Historicals!$E$65)/Base!$D$96 -> 112.14114 | E11: =(SUMPRODUCT(Base!$E$82:$I$82,1/(1+E$8)^Base!$E$83:$I$83)+Base!$I$80*(1+$B11)/(E$8-$B11)/(1+E$8)^(WACC!$C$28+4)-Historicals!$E$79+Historicals!$E$64+Historicals!$E$65)/Base!$D$96 -> 104.60259 | F11: =(SUMPRODUCT(Base!$E$82:$I$82,1/(1+F$8)^Base!$E$83:$I$83)+Base!$I$80*(1+$B11)/(F$8-$B11)/(1+F$8)^(WACC!$C$28+4)-Historicals!$E$79+Historicals!$E$64+Historicals!$E$65)/Base!$D$96 -> 97.98551 | G11: =(SUMPRODUCT(Base!$E$82:$I$82,1/(1+G$8)^Base!$E$83:$I$83)+Base!$I$80*(1+$B11)/(G$8-$B11)/(1+G$8)^(WACC!$C$28+4)-Historicals!$E$79+Historicals!$E$64+Historicals!$E$65)/Base!$D$96 -> 92.131365 | H11: Middle cell should equal the Base sheet's value per share.
B12: 0.035 | C12: =(SUMPRODUCT(Base!$E$82:$I$82,1/(1+C$8)^Base!$E$83:$I$83)+Base!$I$80*(1+$B12)/(C$8-$B12)/(1+C$8)^(WACC!$C$28+4)-Historicals!$E$79+Historicals!$E$64+Historicals!$E$65)/Base!$D$96 -> 128.80295 | D12: =(SUMPRODUCT(Base!$E$82:$I$82,1/(1+D$8)^Base!$E$83:$I$83)+Base!$I$80*(1+$B12)/(D$8-$B12)/(1+D$8)^(WACC!$C$28+4)-Historicals!$E$79+Historicals!$E$64+Historicals!$E$65)/Base!$D$96 -> 118.91564 | E12: =(SUMPRODUCT(Base!$E$82:$I$82,1/(1+E$8)^Base!$E$83:$I$83)+Base!$I$80*(1+$B12)/(E$8-$B12)/(1+E$8)^(WACC!$C$28+4)-Historicals!$E$79+Historicals!$E$64+Historicals!$E$65)/Base!$D$96 -> 110.40208 | F12: =(SUMPRODUCT(Base!$E$82:$I$82,1/(1+F$8)^Base!$E$83:$I$83)+Base!$I$80*(1+$B12)/(F$8-$B12)/(1+F$8)^(WACC!$C$28+4)-Historicals!$E$79+Historicals!$E$64+Historicals!$E$65)/Base!$D$96 -> 102.99549 | G12: =(SUMPRODUCT(Base!$E$82:$I$82,1/(1+G$8)^Base!$E$83:$I$83)+Base!$I$80*(1+$B12)/(G$8-$B12)/(1+G$8)^(WACC!$C$28+4)-Historicals!$E$79+Historicals!$E$64+Historicals!$E$65)/Base!$D$96 -> 96.493908
B13: 0.04 | C13: =(SUMPRODUCT(Base!$E$82:$I$82,1/(1+C$8)^Base!$E$83:$I$83)+Base!$I$80*(1+$B13)/(C$8-$B13)/(1+C$8)^(WACC!$C$28+4)-Historicals!$E$79+Historicals!$E$64+Historicals!$E$65)/Base!$D$96 -> 138.19412 | D13: =(SUMPRODUCT(Base!$E$82:$I$82,1/(1+D$8)^Base!$E$83:$I$83)+Base!$I$80*(1+$B13)/(D$8-$B13)/(1+D$8)^(WACC!$C$28+4)-Historicals!$E$79+Historicals!$E$64+Historicals!$E$65)/Base!$D$96 -> 126.77719 | E13: =(SUMPRODUCT(Base!$E$82:$I$82,1/(1+E$8)^Base!$E$83:$I$83)+Base!$I$80*(1+$B13)/(E$8-$B13)/(1+E$8)^(WACC!$C$28+4)-Historicals!$E$79+Historicals!$E$64+Historicals!$E$65)/Base!$D$96 -> 117.06305 | F13: =(SUMPRODUCT(Base!$E$82:$I$82,1/(1+F$8)^Base!$E$83:$I$83)+Base!$I$80*(1+$B13)/(F$8-$B13)/(1+F$8)^(WACC!$C$28+4)-Historicals!$E$79+Historicals!$E$64+Historicals!$E$65)/Base!$D$96 -> 108.69822 | G13: =(SUMPRODUCT(Base!$E$82:$I$82,1/(1+G$8)^Base!$E$83:$I$83)+Base!$I$80*(1+$B13)/(G$8-$B13)/(1+G$8)^(WACC!$C$28+4)-Historicals!$E$79+Historicals!$E$64+Historicals!$E$65)/Base!$D$96 -> 101.42067
B15: WACC Tapestry's price implies (Base case) | H15: Found by testing: the Base case is worth today's price at about a 10.0% WACC. See the README.

Sheet Historicals
B2: Tapestry, Inc.: Reported Financials
B3: From the FY2026 Form 10-K (fiscal year ended June 27, 2026) and the Q4 FY2026 earnings release. $ in millions. Do not edit.
B5: Income Statement (GAAP)
B6: Line | C6: FY2024 | D6: FY2025 | E6: FY2026 | F6: Units | G6: Source
B7: Net sales | C7: 6671.2 | D7: 7010.7 | E7: 8004.2 | F7: $M | G7: FY2026 10-K, Statements of Operations
B8: Cost of sales | C8: 1781.7 | D8: 1721.8 | E8: 1775.2 | F8: $M | G8: FY2026 10-K
B9: Gross profit | C9: 4889.5 | D9: 5288.9 | E9: 6229 | F9: $M | G9: FY2026 10-K
B10: SG&A expenses | C10: 3749.4 | D10: 4019.1 | E10: 4314.6 | F10: $M | G10: FY2026 10-K
B11: Impairment of goodwill and intangible assets | C11: 0 | D11: 854.8 | E11: 0 | F11: $M | G11: FY2026 10-K (Kate Spade)
B12: Operating income (loss) | C12: 1140.1 | D12: 415 | E12: 1914.4 | F12: $M | G12: FY2026 10-K
B13: Loss on extinguishment of debt | C13: 0 | D13: 120.1 | E13: 0 | F13: $M | G13: FY2026 10-K
B14: Interest expense, net | C14: 125 | D14: 85.4 | E14: 55.2 | F14: $M | G14: FY2026 10-K
B15: Other expense (income) | C15: 3.2 | D15: -6.6 | E15: -1.4 | F15: $M | G15: FY2026 10-K
B16: Income before taxes | C16: 1011.9 | D16: 216.1 | E16: 1860.6 | F16: $M | G16: FY2026 10-K
B17: Provision for income taxes | C17: 195.9 | D17: 32.9 | E17: 332.9 | F17: $M | G17: FY2026 10-K
B18: Net income | C18: 816 | D18: 183.2 | E18: 1527.7 | F18: $M | G18: FY2026 10-K
... B21: Basic shares | C21: 229.2 | D21: 216.8 | E21: 204 | F21: M | G21: FY2026 10-K
B23: Adjusted (Non-GAAP) Results, as Reported by Tapestry
B24: FY2026 adjusted results exclude Stuart Weitzman (sold Aug 4, 2025), a $98.3M IEEPA tariff refund gain and restructuring costs.
B25: Line | D25: FY2025 | E25: FY2026 | F25: Units | G25: Source
B26: Net sales (FY2026 pro forma, excludes Stuart Weitzman) | D26: 7010.7 | E26: 7989.6 | F26: $M | G26: Q4 FY2026 earnings release (8-K Ex. 99.1, Aug 13, 2026), non-GAAP reconciliation
B27: Gross profit | D27: 5288.9 | E27: 6123.1 | F27: $M | G27: Q4 FY2026 earnings release (8-K Ex. 99.1, Aug 13, 2026), non-GAAP reconciliation
B28: SG&A expenses | D28: 3889.4 | E28: 4257.3 | F28: $M | G28: Q4 FY2026 earnings release (8-K Ex. 99.1, Aug 13, 2026), non-GAAP reconciliation
B29: Operating income | D29: 1399.5 | E29: 1865.8 | F29: $M | G29: Q4 FY2026 earnings release (8-K Ex. 99.1, Aug 13, 2026), non-GAAP reconciliation
B30: Interest expense, net | D30: 25.2 | E30: 55.3 | F30: $M | G30: Q4 FY2026 earnings release (8-K Ex. 99.1, Aug 13, 2026), non-GAAP reconciliation
B31: Other expense (income) | E31: -1.5 | F31: $M | G31: Q4 FY2026 earnings release (8-K Ex. 99.1, Aug 13, 2026), non-GAAP reconciliation
B32: Provision for income taxes | D32: 246 | E32: 330 | F32: $M | G32: Q4 FY2026 earnings release (8-K Ex. 99.1, Aug 13, 2026), non-GAAP reconciliation
B33: Net income | D33: 1134.2 | E33: 1482 | F33: $M | G33: Q4 FY2026 earnings release (8-K Ex. 99.1, Aug 13, 2026), non-GAAP reconciliation
B34: Diluted EPS | D34: 5.1 | E34: 7.05 | F34: $ | G34: Q4 FY2026 earnings release (8-K Ex. 99.1, Aug 13, 2026), non-GAAP reconciliation
B36: Net Sales by Brand
B37: Brand | C37: FY2024 | D37: FY2025 | E37: FY2026 | F37: Units | G37: Source
B38: Coach | C38: 5095.3 | D38: 5598.5 | E38: 6914.7 | F38: $M | G38: FY2026 10-K, Segment Information
B39: Kate Spade | C39: 1334.4 | D39: 1197.1 | E39: 1074.9 | F39: $M | G39: FY2026 10-K
B40: Stuart Weitzman (sold Aug 4, 2025) | C40: 241.5 | D40: 215.1 | E40: 14.6 | F40: $M | G40: FY2026 10-K
B41: Total | C41: =SUM(C38:C40) -> 6671.2 | D41: =SUM(D38:D40) -> 7010.7 | E41: =SUM(E38:E40) -> 8004.2 | F41: $M | G41: Ties to net sales
B43: Segment Operating Profit (GAAP)
B44: Segment | C44: FY2024 | D44: FY2025 | E44: FY2026 | F44: Units | G44: Source
B45: Coach | C45: 1651.1 | D45: 1875.3 | E45: 2541.2 | F45: $M | G45: FY2026 10-K, Segment Information
B46: Kate Spade | C46: 132.6 | D46: -769.2 | E46: -10 | F46: $M | G46: FY2026 10-K (FY2025 includes the $854.8M impairment)
B47: Stuart Weitzman | C47: -21.2 | D47: -15.4 | E47: -1 | F47: $M | G47: FY2026 10-K
B48: Unallocated corporate expenses | C48: -622.4 | D48: -675.7 | E48: -615.8 | F48: $M | G48: FY2026 10-K
B49: Total operating income | C49: =SUM(C45:C48) -> 1140.1 | D49: =SUM(D45:D48) -> 415 | E49: =SUM(E45:E48) -> 1914.4 | F49: $M | G49: Ties to the income statement
B51: Net Sales by Product and Region
B52: Line | C52: FY2024 | D52: FY2025 | E52: FY2026 | F52: Units | G52: Source
B53: Handbags | C53: 3610.9 | D53: 3846.3 | E53: 4611.2 | F53: $M | G53: FY2026 10-K, Net Sales by Product Category
B54: Accessories | C54: 1714.9 | D54: 1809.3 | E54: 2232.9 | F54: $M | G54: FY2026 10-K
B55: Footwear | C55: 624.9 | D55: 612.8 | E55: 471.2 | F55: $M | G55: FY2026 10-K
B56: Other | C56: 720.5 | D56: 742.3 | E56: 688.9 | F56: $M | G56: FY2026 10-K
B57: United States | C57: 3949.7 | D57: 4208.1 | E57: 4697.4 | F57: $M | G57: FY2026 10-K, Geographical Area Information
B58: China | C58: 1012.6 | D58: 1059.7 | E58: 1398.7 | F58: $M | G58: FY2026 10-K
B59: Japan | C59: 554.4 | D59: 514.8 | E59: 465.7 | F59: $M | G59: FY2026 10-K
B60: Other | C60: 1154.5 | D60: 1228.1 | E60: 1442.4 | F60: $M | G60: FY2026 10-K
B62: Balance Sheet
B63: Line | D63: Jun 28, 2025 | E63: Jun 27, 2026 | F63: Units | G63: Source
B64: Cash and cash equivalents | D64: 1100 | E64: 974.7 | F64: $M | G64: FY2026 10-K, Balance Sheets
B65: Short-term investments | D65: 19.6 | E65: 177.3 | F65: $M | G65: FY2026 10-K
B66: Trade accounts receivable | D66: 239.3 | E66: 237.1 | F66: $M | G66: FY2026 10-K
B67: Inventories | D67: 860.7 | E67: 826.2 | F67: $M | G67: FY2026 10-K
B68: Income tax receivable, prepaid and other current assets | D68: =277.3+133.8+98.5+176.4 -> 686 | E68: =269.3+155.2+242.5+0 -> 667 | F68: $M | G68: FY2026 10-K (FY2025 includes $176.4M held for sale)
B69: Property and equipment, net | D69: 489.5 | E69: 502.1 | F69: $M | G69: FY2026 10-K
B70: Operating lease right-of-use assets | D70: 1331 | E70: 1417.2 | F70: $M | G70: FY2026 10-K
B71: Goodwill | D71: 983.3 | E71: 957.7 | F71: $M | G71: FY2026 10-K
B72: Intangible assets | D72: 719.6 | E72: 716.5 | F72: $M | G72: FY2026 10-K
B73: Deferred income taxes and other assets | D73: =33.8+117.7 -> 151.5 | E73: =35.7+180.2 -> 215.9 | F73: $M | G73: FY2026 10-K
B74: Total assets | D74: =SUM(D64:D73) -> 6580.5 | E74: =SUM(E64:E73) -> 6691.7 | F74: $M | G74: Ties to $6,580.5M and $6,691.7M
B75: Accounts payable | D75: 456.1 | E75: 582.3 | F75: $M | G75: FY2026 10-K
B76: Accrued liabilities | D76: 736.9 | E76: 754.9 | F76: $M | G76: FY2026 10-K
B77: Current operating lease liabilities | D77: 299 | E77: 307.8 | F77: $M | G77: FY2026 10-K
B78: Current debt and liabilities held for sale | D78: =16.7+48.2 -> 64.9 | E78: 0 | F78: $M | G78: FY2026 10-K
B79: Long-term debt | D79: 2377.9 | E79: 2379 | F79: $M | G79: FY2026 10-K
B80: Long-term operating lease liabilities | D80: 1205.6 | E80: 1266.2 | F80: $M | G80: FY2026 10-K
B81: Deferred income taxes and other liabilities | D81: =79.8+502.5 -> 582.3 | E81: =172.8+536.6 -> 709.4 | F81: $M | G81: FY2026 10-K
B82: Total liabilities | D82: =SUM(D75:D81) -> 5722.7 | E82: =SUM(E75:E81) -> 5999.6 | F82: $M | G82: Ties to $5,722.7M and $5,999.6M
B83: Stockholders' equity | D83: 857.8 | E83: 692.1 | F83: $M | G83: FY2026 10-K
B84: Check: assets less liabilities and equity | D84: =D74-D82-D83 -> 0 | E84: =E74-E82-E83 -> 0 | F84: $M | G84: Should be zero
B86: Cash Flow Highlights
B87: Line | C87: FY2024 | D87: FY2025 | E87: FY2026 | F87: Units | G87: Source
B88: Net cash from operating activities | C88: 1255.6 | D88: 1216.6 | E88: 1978.5 | F88: $M | G88: FY2026 10-K, Statements of Cash Flows
B89: Purchases of property and equipment | C89: -108.9 | D89: -122.7 | E89: -166 | F89: $M | G89: FY2026 10-K
B90: Depreciation and amortization | C90: 174 | D90: 162.9 | E90: 160.8 | F90: $M | G90: FY2026 10-K
B91: Amortization of cloud computing arrangements | C91: 55 | D91: 62 | E91: 56.4 | F91: $M | G91: FY2026 10-K
B92: Share-based compensation | C92: 85.9 | D92: 87.3 | E92: 104.5 | F92: $M | G92: FY2026 10-K
B93: Dividends paid | C93: -321.4 | D93: -299.3 | E93: -326.1 | F93: $M | G93: FY2026 10-K
B94: Share repurchases | C94: 0 | D94: -1718.7 | E94: -1554.6 | F94: $M | G94: FY2026 10-K
B96: Senior Notes Outstanding (June 27, 2026)
B97: Note | C97: Coupon | D97: Principal | E97: Fair value | F97: Units | G97: Source
B98: 4.125% Senior Notes due 2027 | C98: 0.04125 | D98: 396.6 | E98: 394.9 | F98: $M | G98: FY2026 10-K, Debt note
B99: 5.100% Senior Notes due March 11, 2030 | C99: 0.051 | D99: 750 | E99: 757.4 | F99: $M | G99: FY2026 10-K; maturity date from the Dec 4, 2024 pricing term sheet
B100: 3.050% Senior Notes due 2032 | C100: 0.0305 | D100: 500 | E100: 454.2 | F100: $M | G100: FY2026 10-K
B101: 5.500% Senior Notes due March 11, 2035 | C101: 0.055 | D101: 750 | E101: 757.7 | F101: $M | G101: FY2026 10-K; maturity date from the Dec 4, 2024 pricing term sheet
B103: Other Facts
B104: Fact | C104: Value | F104: Units | G104: Source
B105: Shares outstanding, July 31, 2026 | C105: 199.39168 | F105: M | G105: FY2026 10-K cover page
B106: Dilutive securities in FY2026 diluted EPS | C106: 6.2 | F106: M | G106: FY2026 10-K, Earnings per Share
B107: New customers acquired in FY2026 | C107: 11 | F107: M | G107: Q4 FY2026 earnings release (8-K Ex. 99.1, Aug 13, 2026), non-GAAP reconciliation: 'approximately 11.0 million', about 35% Gen Z
B108: Coach directly operated stores, June 27, 2026 | C108: 973 | F108: # | G108: Q4 FY2026 earnings release (8-K Ex. 99.1, Aug 13, 2026), non-GAAP reconciliation (931 a year earlier)
B109: Kate Spade directly operated stores, June 27, 2026 | C109: 326 | F109: # | G109: Q4 FY2026 earnings release (8-K Ex. 99.1, Aug 13, 2026), non-GAAP reconciliation (360 a year earlier)
B110: Shares repurchased in FY2026 | C110: 11.5 | F110: M | G110: Q4 FY2026 earnings release (8-K Ex. 99.1, Aug 13, 2026), non-GAAP reconciliation: about 11.5M shares at about $118 average

Sheet Market Data
B2: Market Data
B3: Prices, rates and guidance used in the model, with sources. Do not edit.
B5: Tapestry Stock and Street View
B6: Item | C6: Value | F6: Units | G6: Source
B7: Share price, close Oct 8, 2026 | C7: 115.82 | F7: $ | G7: stockanalysis.com/stocks/tpr
B8: 52-week high | C8: 164.8 | F8: $ | G8: stockanalysis.com/stocks/tpr (early August 2026)
B9: 52-week low | C9: 93 | F9: $ | G9: stockanalysis.com/stocks/tpr
B10: Beta (5-year) | C10: 1.43 | F10: x | G10: stockanalysis.com/stocks/tpr/statistics
B11: Average analyst price target | C11: 166.5 | F11: $ | G11: stockanalysis.com (22 analysts, consensus Buy)
B12: Lowest analyst price target | C12: 138 | F12: $ | G12: MarketBeat, Sep 21, 2026
B13: Highest analyst price target | C13: 232 | F13: $ | G13: MarketBeat, Sep 21, 2026
B15: FY2027 Guidance (Aug 13, 2026)
B16: Item | C16: Low | D16: High | F16: Units | G16: Source
B17: Revenue | C17: 8400 | D17: 8500 | F17: $M | G17: Q4 FY2026 earnings release (8-K Ex. 99.1, Aug 13, 2026), non-GAAP reconciliation (mid-single digit growth, includes a 53rd week)
B18: Adjusted EPS | C18: 7.8 | D18: 7.9 | F18: $ | G18: Q4 FY2026 earnings release (8-K Ex. 99.1, Aug 13, 2026), non-GAAP reconciliation
B19: Operating margin expansion | C19: 0.005 | D19: 0.005 | F19: % | G19: Q4 FY2026 earnings release (8-K Ex. 99.1, Aug 13, 2026), non-GAAP reconciliation: 'approximately 50 bps'
B20: Adjusted free cash flow | C20: 1700 | D20: 1700 | F20: $M | G20: Q4 FY2026 earnings release (8-K Ex. 99.1, Aug 13, 2026), non-GAAP reconciliation: 'approaching $1.7 billion'
B21: CapEx and cloud computing costs | C21: 300 | D21: 300 | F21: $M | G21: Q4 FY2026 earnings release (8-K Ex. 99.1, Aug 13, 2026), non-GAAP reconciliation
B22: Share repurchases | C22: 1350 | D22: 1350 | F22: $M | G22: Q4 FY2026 earnings release (8-K Ex. 99.1, Aug 13, 2026), non-GAAP reconciliation
B23: Annual dividend per share | C23: 1.85 | D23: 1.85 | F23: $ | G23: Q4 FY2026 earnings release (8-K Ex. 99.1, Aug 13, 2026), non-GAAP reconciliation: $0.4625 a quarter
B25: Rates
B26: Item | C26: Value | F26: Units | G26: Source
B27: 10-year Treasury, Oct 7, 2026 | C27: 0.0528 | F27: % | G27: home.treasury.gov daily par yield curve. Highest since 2002 (Forbes, Oct 7, 2026)
B28: 10-year Treasury, Jun 26, 2026 | C28: 0.0438 | F28: % | G28: home.treasury.gov daily par yield curve
B29: 1-year Treasury, Oct 7, 2026 | C29: 0.0442 | F29: % | G29: home.treasury.gov daily par yield curve
B30: Implied equity risk premium (S&P 500) | C30: 0.0423 | F30: % | G30: Aswath Damodaran, January 2026 (via BVWire)
B31: Tapestry senior note ratings (Moody's / S&P) | C31: Baa2 / BBB | G31: Pricing term sheet, Dec 4, 2024 (expected ratings)
